Workbook

Sheet ORC DOM_2025
A1: ORÇAMENTO DOMÉSTICO
A5: MESES DO ANO | B5: % | C5: 46023 | D5: % | E5: 46054 | F5: % | G5: 46082 | H5: % | I5: 45748 | J5: % | K5: 45778 | L5: % | M5: 45809 | N5: % | O5: 45839 | P5: % | Q5: 45870 | R5: % | S5: 45901 | T5: % | U5: 45931 | V5: % | W5: 45962 | X5: % | Y5: 45992 | Z5: TOTAL ANO
A6: Receitas Fixas | C6: ATUAL | E6: SO FIXO | G6: 60% TOTAL | I6: 50% TT + COMPRAS CASA
A7: Fonte de Renda 1 (Líquido) - dia 1 | B7: =IFERROR(C7/C$20,0) -> 0.61823818 | C7: =1250+200+250-(1700*18.2%)-150 -> 1240.6 | D7: =IFERROR(E7/E$20,0) -> 0.40203932 | E7: =1250+200+250-(1700*18.2%)-300 -> 1090.6 | F7: =IFERROR(G7/G$20,0) -> 0.39467732 | G7: =1250+200+250-(1700*18.2%)-300 -> 1090.6 | H7: =IFERROR(I7/I$20,0) -> 0.41790724 | I7: =1250+200+250-(1700*18.2%)-300 -> 1090.6 | J7: =IFERROR(K7/K$20,0) -> 0 | L7: =IFERROR(M7/M$20,0) -> 0 | N7: =IFERROR(O7/O$20,0) -> 0 | P7: =IFERROR(Q7/Q$20,0) -> 0 | R7: =IFERROR(S7/S$20,0) -> 0 | T7: =IFERROR(U7/U$20,0) -> 0 | V7: =IFERROR(W7/W$20,0) -> 0 | X7: =IFERROR(Y7/Y$20,0) -> 0 | Z7: =C7+E7+G7+I7+K7+M7+O7+Q7+S7+U7+W7+Y7 -> 4512.4
A8: Pensão meninas | B8: =IFERROR(C8/C$20,0) -> 0.094684228 | C8: 190 | D8: =IFERROR(E8/E$20,0) -> 0.070041693 | E8: 190 | F8: =IFERROR(G8/G$20,0) -> 0.068759115 | G8: 190 | H8: =IFERROR(I8/I$20,0) -> 0.07280614 | I8: 190 | J8: =IFERROR(K8/K$20,0) -> 0 | L8: =IFERROR(M8/M$20,0) -> 0 | N8: =IFERROR(O8/O$20,0) -> 0 | P8: =IFERROR(Q8/Q$20,0) -> 0 | R8: =IFERROR(S8/S$20,0) -> 0 | T8: =IFERROR(U8/U$20,0) -> 0 | V8: =IFERROR(W8/W$20,0) -> 0 | X8: =IFERROR(Y8/Y$20,0) -> 0 | Z8: =C8+E8+G8+I8+K8+M8+O8+Q8+S8+U8+W8+Y8 -> 760
A9: Outros (Seg Social) - dia 16 | B9: =IFERROR(C9/C$20,0) -> 0.19139669 | C9: =(384.07) -> 384.07 | D9: =IFERROR(E9/E$20,0) -> 0.14158375 | E9: =(384.07) -> 384.07 | F9: =IFERROR(G9/G$20,0) -> 0.13899112 | G9: =(384.07) -> 384.07 | H9: =IFERROR(I9/I$20,0) -> 0.14717186 | I9: =(384.07) -> 384.07 | J9: =IFERROR(K9/K$20,0) -> 0 | L9: =IFERROR(M9/M$20,0) -> 0 | N9: =IFERROR(O9/O$20,0) -> 0 | P9: =IFERROR(Q9/Q$20,0) -> 0 | R9: =IFERROR(S9/S$20,0) -> 0 | T9: =IFERROR(U9/U$20,0) -> 0 | V9: =IFERROR(W9/W$20,0) -> 0 | X9: =IFERROR(Y9/Y$20,0) -> 0 | Z9: =C9+E9+G9+I9+K9+M9+O9+Q9+S9+U9+W9+Y9 -> 1536.28
A10: Vale refeição Norma | B10: =IFERROR(C10/C$20,0) -> 0.095680904 | C10: =9.6*20 -> 192 | D10: =IFERROR(E10/E$20,0) -> 0.070778974 | E10: =9.6*20 -> 192 | F10: =IFERROR(G10/G$20,0) -> 0.069482895 | G10: =9.6*20 -> 192 | H10: =IFERROR(I10/I$20,0) -> 0.073572521 | I10: =9.6*20 -> 192 | J10: =IFERROR(K10/K$20,0) -> 0
A11: Vale refeição Fernando | B11: =IFERROR(C11/C$20,0) -> 0 | D11: =IFERROR(E11/E$20,0) -> 0.070778974 | E11: =9.6*20 -> 192 | F11: =IFERROR(G11/G$20,0) -> 0.073825576 | G11: =10.2*20 -> 204 | H11: =IFERROR(I11/I$20,0) -> 0.078170803 | I11: =G11 -> 204 | J11: =IFERROR(K11/K$20,0) -> 0
A12: Apoio Fernando | B12: =IFERROR(C12/C$20,0) -> 0 | D12: =IFERROR(E12/E$20,0) -> 0.24477729 | E12: =SUM(E32:E40)-E11 -> 664 | F12: =IFERROR(G12/G$20,0) -> 0.25426397 | G12: =G31*60%-G11 -> 702.6 | H12: =IFERROR(I12/I$20,0) -> 0.21037143 | I12: =(I31*50%)-I11 -> 549 | J12: =IFERROR(K12/K$20,0) -> 0 | L12: =IFERROR(M12/M$20,0) -> 0 | N12: =IFERROR(O12/O$20,0) -> 0 | P12: =IFERROR(Q12/Q$20,0) -> 0 | R12: =IFERROR(S12/S$20,0) -> 0 | T12: =IFERROR(U12/U$20,0) -> 0 | V12: =IFERROR(W12/W$20,0) -> 0 | X12: =IFERROR(Y12/Y$20,0) -> 0 | Z12: =C12+E12+G12+I12+K12+M12+O12+Q12+S12+U12+W12+Y12 -> 1915.6
A13: Total Receitas Fixas | B13: =IFERROR(C13/C$20,0) -> 1 | C13: =SUM(C7:C12) -> 2006.67 | D13: =IFERROR(E13/E$20,0) -> 1 | E13: =SUM(E7:E12) -> 2712.67 | F13: =IFERROR(G13/G$20,0) -> 1 | G13: =SUM(G7:G12) -> 2763.27 | H13: =IFERROR(I13/I$20,0) -> 1 | I13: =SUM(I7:I12) -> 2609.67 | J13: =IFERROR(K13/K$20,0) -> 0 | K13: =SUM(K7:K12) -> 0 | L13: =IFERROR(M13/M$20,0) -> 0 | M13: =SUM(M7:M12) -> 0 | N13: =IFERROR(O13/O$20,0) -> 0 | O13: =SUM(O7:O12) -> 0 | P13: =IFERROR(Q13/Q$20,0) -> 0 | Q13: =SUM(Q7:Q12) -> 0 | R13: =IFERROR(S13/S$20,0) -> 0 | S13: =SUM(S7:S12) -> 0 | T13: =IFERROR(U13/U$20,0) -> 0 | U13: =SUM(U7:U12) -> 0 | V13: =IFERROR(W13/W$20,0) -> 0 | W13: =SUM(W7:W12) -> 0 | X13: =IFERROR(Y13/Y$20,0) -> 0 | Y13: =SUM(Y7:Y12) -> 0 | Z13: =C13+E13+G13+I13+K13+M13+O13+Q13+S13+U13+W13+Y13 -> 10092.28
A14: Receitas Variáveis Não Tributadas
A15: 13o. Salário Líquido | B15: =IFERROR(C15/C$20,0) -> 0 | D15: =IFERROR(E15/E$20,0) -> 0 | F15: =IFERROR(G15/G$20,0) -> 0 | H15: =IFERROR(I15/I$20,0) -> 0 | J15: =IFERROR(K15/K$20,0) -> 0 | L15: =IFERROR(M15/M$20,0) -> 0 | N15: =IFERROR(O15/O$20,0) -> 0 | P15: =IFERROR(Q15/Q$20,0) -> 0 | R15: =IFERROR(S15/S$20,0) -> 0 | T15: =IFERROR(U15/U$20,0) -> 0 | V15: =IFERROR(W15/W$20,0) -> 0 | X15: =IFERROR(Y15/Y$20,0) -> 0 | Z15: =C15+E15+G15+I15+K15+M15+O15+Q15+S15+U15+W15+Y15 -> 0
A16: Férias | B16: =IFERROR(C16/C$20,0) -> 0 | D16: =IFERROR(E16/E$20,0) -> 0 | F16: =IFERROR(G16/G$20,0) -> 0 | H16: =IFERROR(I16/I$20,0) -> 0 | J16: =IFERROR(K16/K$20,0) -> 0 | L16: =IFERROR(M16/M$20,0) -> 0 | N16: =IFERROR(O16/O$20,0) -> 0 | P16: =IFERROR(Q16/Q$20,0) -> 1 | Q16: 1000 | R16: =IFERROR(S16/S$20,0) -> 0 | T16: =IFERROR(U16/U$20,0) -> 0 | V16: =IFERROR(W16/W$20,0) -> 1 | W16: 1000 | X16: =IFERROR(Y16/Y$20,0) -> 0 | Z16: =C16+E16+G16+I16+K16+M16+O16+Q16+S16+U16+W16+Y16 -> 2000
A17: Bônus e extras | B17: =IFERROR(C17/C$20,0) -> 0 | D17: =IFERROR(E17/E$20,0) -> 0 | F17: =IFERROR(G17/G$20,0) -> 0 | H17: =IFERROR(I17/I$20,0) -> 0 | J17: =IFERROR(K17/K$20,0) -> 0 | L17: =IFERROR(M17/M$20,0) -> 0 | N17: =IFERROR(O17/O$20,0) -> 0 | P17: =IFERROR(Q17/Q$20,0) -> 0 | R17: =IFERROR(S17/S$20,0) -> 0 | T17: =IFERROR(U17/U$20,0) -> 0 | V17: =IFERROR(W17/W$20,0) -> 0 | X17: =IFERROR(Y17/Y$20,0) -> 0 | Z17: =C17+E17+G17+I17+K17+M17+O17+Q17+S17+U17+W17+Y17 -> 0
A18: Total Receitas Variáveis | B18: =IFERROR(C18/C$20,0) -> 0 | C18: =SUM(C15:C17) -> 0 | D18: =IFERROR(E18/E$20,0) -> 0 | E18: =SUM(E15:E17) -> 0 | F18: =IFERROR(G18/G$20,0) -> 0 | G18: =SUM(G15:G17) -> 0 | H18: =IFERROR(I18/I$20,0) -> 0 | I18: =SUM(I15:I17) -> 0 | J18: =IFERROR(K18/K$20,0) -> 0 | K18: =SUM(K15:K17) -> 0 | L18: =IFERROR(M18/M$20,0) -> 0 | M18: =SUM(M15:M17) -> 0 | N18: =IFERROR(O18/O$20,0) -> 0 | O18: =SUM(O15:O17) -> 0 | P18: =IFERROR(Q18/Q$20,0) -> 1 | Q18: =SUM(Q15:Q17) -> 1000 | R18: =IFERROR(S18/S$20,0) -> 0 | S18: =SUM(S15:S17) -> 0 | T18: =IFERROR(U18/U$20,0) -> 0 | U18: =SUM(U15:U17) -> 0 | V18: =IFERROR(W18/W$20,0) -> 1 | W18: =SUM(W15:W17) -> 1000 | X18: =IFERROR(Y18/Y$20,0) -> 0 | Y18: =SUM(Y15:Y17) -> 0 | Z18: =SUM(Z15:Z17) -> 2000
A20: Renda Total | B20: 1 | C20: =C18+C13 -> 2006.67 | D20: 1 | E20: =E18+E13 -> 2712.67 | F20: 1 | G20: =G18+G13 -> 2763.27 | H20: 1 | I20: =I18+I13 -> 2609.67 | J20: 1 | K20: =K18+K13 -> 0 | L20: 1 | M20: =M18+M13 -> 0 | N20: 1 | O20: =O18+O13 -> 0 | P20: 1 | Q20: =Q18+Q13 -> 1000 | R20: 1 | S20: =S18+S13 -> 0 | T20: 1 | U20: =U18+U13 -> 0 | V20: 1 | W20: =W18+W13 -> 1000 | X20: 1 | Y20: =Y18+Y13 -> 0 | Z20: =Z18+Z13 -> 12092.28
A22: BOLETO PESSOAL | B22: =IFERROR(C22/C$20,0) -> 0 | C22: =SUM(C23:C28) -> 0 | D22: =IFERROR(E22/E$20,0) -> 0.092160123 | E22: =SUM(E23:E28) -> 250 | F22: =IFERROR(G22/G$20,0) -> 0.09047252 | G22: =SUM(G23:G28) -> 250 | H22: =IFERROR(I22/I$20,0) -> 0.095797553 | I22: =SUM(I23:I28) -> 250 | J22: =IFERROR(K22/K$20,0) -> 0 | K22: =SUM(K23:K28) -> 250 | L22: =IFERROR(M22/M$20,0) -> 0 | M22: =SUM(M23:M28) -> 250 | N22: =IFERROR(O22/O$20,0) -> 0 | O22: =SUM(O23:O28) -> 250 | P22: =IFERROR(Q22/Q$20,0) -> 1.25 | Q22: =SUM(Q23:Q28) -> 1250 | R22: =IFERROR(S22/S$20,0) -> 0 | S22: =SUM(S23:S28) -> 250 | T22: =IFERROR(U22/U$20,0) -> 0 | U22: =SUM(U23:U28) -> 250 | V22: =IFERROR(W22/W$20,0) -> 1.25 | W22: =SUM(W23:W28) -> 1250 | X22: =IFERROR(Y22/Y$20,0) -> 0 | Y22: =SUM(Y23:Y28) -> 250 | Z22: =C22+E22+G22+I22+K22+M22+O22+Q22+S22+U22+W22+Y22 -> 4750
A23: META - 1 ano ( pagar divida bitcoin) | B23: =IFERROR(C23/C$20,0) -> 0 | D23: =IFERROR(E23/E$20,0) -> 0 | F23: =IFERROR(G23/G$20,0) -> 0 | H23: =IFERROR(I23/I$20,0) -> 0 | J23: =IFERROR(K23/K$20,0) -> 0 | L23: =IFERROR(M23/M$20,0) -> 0 | N23: =IFERROR(O23/O$20,0) -> 0 | P23: =IFERROR(Q23/Q$20,0) -> 0 | R23: =IFERROR(S23/S$20,0) -> 0 | T23: =IFERROR(U23/U$20,0) -> 0 | V23: =IFERROR(W23/W$20,0) -> 0 | W23: =U23 | X23: =IFERROR(Y23/Y$20,0) -> 0 | Z23: =C23+E23+G23+I23+K23+M23+O23+Q23+S23+U23+W23+Y23 -> 0
A24: META - 1 ano (quitação do carro) | B24: =IFERROR(C24/C$20,0) -> 0 | D24: =IFERROR(E24/E$20,0) -> 0 | F24: =IFERROR(G24/G$20,0) -> 0 | H24: =IFERROR(I24/I$20,0) -> 0 | J24: =IFERROR(K24/K$20,0) -> 0 | L24: =IFERROR(M24/M$20,0) -> 0 | N24: =IFERROR(O24/O$20,0) -> 0 | P24: =IFERROR(Q24/Q$20,0) -> 0 | R24: =IFERROR(S24/S$20,0) -> 0 | T24: =IFERROR(U24/U$20,0) -> 0 | V24: =IFERROR(W24/W$20,0) -> 0 | W24: =U24 | X24: =IFERROR(Y24/Y$20,0) -> 0 | Z24: =C24+E24+G24+I24+K24+M24+O24+Q24+S24+U24+W24+Y24 -> 0
A25: META - 1 ano (Viagem Brasil) | B25: =IFERROR(C25/C$20,0) -> 0 | D25: =IFERROR(E25/E$20,0) -> 0.092160123 | E25: 250 | F25: =IFERROR(I25/G$20,0) -> 0.09047252 | G25: 250 | H25: =IFERROR(#REF!/I$20,0) -> 0 | I25: 250 | J25: =IFERROR(K25/K$20,0) -> 0 | K25: 250 | L25: =IFERROR(M25/M$20,0) -> 0 | M25: 250 | N25: =IFERROR(O25/O$20,0) -> 0 | O25: 250 | P25: =IFERROR(Q25/Q$20,0) -> 1.25 | Q25: 1250 | R25: =IFERROR(S25/S$20,0) -> 0 | S25: 250 | T25: =IFERROR(U25/U$20,0) -> 0 | U25: 250 | V25: =IFERROR(W25/W$20,0) -> 1.25 | W25: 1250 | X25: =IFERROR(Y25/Y$20,0) -> 0 | Y25: 250 | Z25: =C25+E25+G25+I25+K25+M25+O25+Q25+S25+U25+W25+Y25 -> 4750
A26: META - 8 meses ( Férias Verão) | B26: =IFERROR(C26/C$20,0) -> 0 | D26: =IFERROR(E26/E$20,0) -> 0 | F26: =IFERROR(I26/G$20,0) -> 0 | H26: =IFERROR(#REF!/I$20,0) -> 0 | J26: =IFERROR(K26/K$20,0) -> 0 | L26: =IFERROR(M26/M$20,0) -> 0 | N26: =IFERROR(O26/O$20,0) -> 0 | P26: =IFERROR(Q26/Q$20,0) -> 0 | R26: =IFERROR(S26/S$20,0) -> 0 | T26: =IFERROR(U26/U$20,0) -> 0 | V26: =IFERROR(W26/W$20,0) -> 0 | X26: =IFERROR(Y26/Y$20,0) -> 0 | Z26: =C26+E26+G26+I26+K26+M26+O26+Q26+S26+U26+W26+Y26 -> 0
A27: METONA ( Casa Própria - 10 anos ) | B27: =IFERROR(C27/C$20,0) -> 0 | D27: =IFERROR(E27/E$20,0) -> 0 | F27: =IFERROR(G27/G$20,0) -> 0 | H27: =IFERROR(I27/I$20,0) -> 0 | J27: =IFERROR(K27/K$20,0) -> 0 | L27: =IFERROR(M27/M$20,0) -> 0 | N27: =IFERROR(O27/O$20,0) -> 0 | P27: =IFERROR(Q27/Q$20,0) -> 0 | R27: =IFERROR(S27/S$20,0) -> 0 | T27: =IFERROR(U27/U$20,0) -> 0 | V27: =IFERROR(W27/W$20,0) -> 0 | X27: =IFERROR(Y27/Y$20,0) -> 0 | Z27: =C27+E27+G27+I27+K27+M27+O27+Q27+S27+U27+W27+Y27 -> 0
A28: METAZONA ( Aposentadoria - 30 anos ) | B28: =IFERROR(C28/C$20,0) -> 0 | D28: =IFERROR(E28/E$20,0) -> 0 | F28: =IFERROR(G28/G$20,0) -> 0 | H28: =IFERROR(I28/I$20,0) -> 0 | J28: =IFERROR(K28/K$20,0) -> 0 | L28: =IFERROR(M28/M$20,0) -> 0 | N28: =IFERROR(O28/O$20,0) -> 0 | P28: =IFERROR(Q28/Q$20,0) -> 0 | R28: =IFERROR(S28/S$20,0) -> 0 | T28: =IFERROR(U28/U$20,0) -> 0 | V28: =IFERROR(W28/W$20,0) -> 0 | X28: =IFERROR(Y28/Y$20,0) -> 0 | Z28: =C28+E28+G28+I28+K28+M28+O28+Q28+S28+U28+W28+Y28 -> 0
A29: TOTAL BOLETO PESSOAL (30%) | B29: =IFERROR(C29/C$20,0) -> 0 | C29: =C22 -> 0 | D29: =IFERROR(E29/E$20,0) -> 0.092160123 | E29: =E22 -> 250 | F29: =IFERROR(G29/G$20,0) -> 0.09047252 | G29: =G22 -> 250 | H29: =IFERROR(I29/I$20,0) -> 0.095797553 | I29: =I22 -> 250 | J29: =IFERROR(K29/K$20,0) -> 0 | K29: =K22 -> 250 | L29: =IFERROR(M29/M$20,0) -> 0 | M29: =M22 -> 250 | N29: =IFERROR(O29/O$20,0) -> 0 | O29: =O22 -> 250 | P29: =IFERROR(Q29/Q$20,0) -> 1.25 | Q29: =Q22 -> 1250 | R29: =IFERROR(S29/S$20,0) -> 0 | S29: =S22 -> 250 | T29: =IFERROR(U29/U$20,0) -> 0 | U29: =U22 -> 250 | V29: =IFERROR(W29/W$20,0) -> 1.25 | W29: =W22 -> 1250 | X29: =IFERROR(Y29/Y$20,0) -> 0 | Y29: =Y22 -> 250 | Z29: =SUM(Z23:Z28) -> 4750
A31: HABITAÇÃO | B31: =IFERROR(C31/C$20,0) -> 0.67350386 | C31: =SUM(C32:C45) -> 1351.5 | D31: =IFERROR(E31/E$20,0) -> 0.55701578 | E31: =SUM(E32:E45) -> 1511 | F31: =IFERROR(G31/G$20,0) -> 0.54681591 | G31: =SUM(G32:G45) -> 1511 | H31: =IFERROR(I31/I$20,0) -> 0.57708446 | I31: =SUM(I32:I45) -> 1506 | J31: =IFERROR(K31/K$20,0) -> 0 | K31: =SUM(K32:K45) -> 1506 | L31: =IFERROR(M31/M$20,0) -> 0 | M31: =SUM(M32:M45) -> 1506 | N31: =IFERROR(O31/O$20,0) -> 0 | O31: =SUM(O32:O45) -> 1506 | P31: =IFERROR(Q31/Q$20,0) -> 1.506 | Q31: =SUM(Q32:Q45) -> 1506 | R31: =IFERROR(S31/S$20,0) -> 0 | S31: =SUM(S32:S45) -> 1506 | T31: =IFERROR(U31/U$20,0) -> 0 | U31: =SUM(U32:U45) -> 1506 | V31: =IFERROR(W31/W$20,0) -> 1.506 | W31: =SUM(W32:W45) -> 1506 | X31: =IFERROR(Y31/Y$20,0) -> 0 | Y31: =SUM(Y32:Y45) -> 1506 | Z31: =C31+E31+G31+I31+K31+M31+O31+Q31+S31+U31+W31+Y31 -> 17927.5
A32: Aluguel | B32: =IFERROR(C32/C$20,0) -> 0.34883663 | C32: 700 | D32: =IFERROR(E32/E$20,0) -> 0.25804834 | E32: 700 | F32: =IFERROR(G32/G$20,0) -> 0.25332306 | G32: 700 | H32: =IFERROR(I32/I$20,0) -> 0.26823315 | I32: 700 | J32: =IFERROR(K32/K$20,0) -> 0 | K32: 700 | L32: =IFERROR(M32/M$20,0) -> 0 | M32: 700 | N32: =IFERROR(O32/O$20,0) -> 0 | O32: 700 | P32: =IFERROR(Q32/Q$20,0) -> 0.7 | Q32: 700 | R32: =IFERROR(S32/S$20,0) -> 0 | S32: 700 | T32: =IFERROR(U32/U$20,0) -> 0 | U32: 700 | V32: =IFERROR(W32/W$20,0) -> 0.7 | W32: 700 | X32: =IFERROR(Y32/Y$20,0) -> 0 | Y32: 700 | Z32: =C32+E32+G32+I32+K32+M32+O32+Q32+S32+U32+W32+Y32 -> 8400
A33: Condomínio | B33: =IFERROR(C33/C$20,0) -> 0 | D33: =IFERROR(E33/E$20,0) -> 0 | F33: =IFERROR(G33/G$20,0) -> 0 | H33: =IFERROR(I33/I$20,0) -> 0 | J33: =IFERROR(K33/K$20,0) -> 0 | L33: =IFERROR(M33/M$20,0) -> 0 | N33: =IFERROR(O33/O$20,0) -> 0 | P33: =IFERROR(Q33/Q$20,0) -> 0 | R33: =IFERROR(S33/S$20,0) -> 0 | T33: =IFERROR(U33/U$20,0) -> 0 | V33: =IFERROR(W33/W$20,0) -> 0 | X33: =IFERROR(Y33/Y$20,0) -> 0 | Z33: =C33+E33+G33+I33+K33+M33+O33+Q33+S33+U33+W33+Y33 -> 0
A34: IPTU | B34: =IFERROR(C34/C$20,0) -> 0 | D34: =IFERROR(E34/E$20,0) -> 0 | F34: =IFERROR(G34/G$20,0) -> 0 | H34: =IFERROR(I34/I$20,0) -> 0 | J34: =IFERROR(K34/K$20,0) -> 0 | L34: =IFERROR(M34/M$20,0) -> 0 | N34: =IFERROR(O34/O$20,0) -> 0 | P34: =IFERROR(Q34/Q$20,0) -> 0 | R34: =IFERROR(S34/S$20,0) -> 0 | T34: =IFERROR(U34/U$20,0) -> 0 | V34: =IFERROR(W34/W$20,0) -> 0 | X34: =IFERROR(Y34/Y$20,0) -> 0 | Z34: =C34+E34+G34+I34+K34+M34+O34+Q34+S34+U34+W34+Y34 -> 0
A35: Conta de água | B35: =IFERROR(C35/C$20,0) -> 0.024916902 | C35: 50 | D35: =IFERROR(E35/E$20,0) -> 0.018432025 | E35: 50 | F35: =IFERROR(G35/G$20,0) -> 0.018094504 | G35: 50 | H35: =IFERROR(I35/I$20,0) -> 0.01724356 | I35: 45 | J35: =IFERROR(K35/K$20,0) -> 0 | K35: 45 | L35: =IFERROR(M35/M$20,0) -> 0 | M35: 45 | N35: =IFERROR(O35/O$20,0) -> 0 | O35: 45 | P35: =IFERROR(Q35/Q$20,0) -> 0.045 | Q35: 45 | R35: =IFERROR(S35/S$20,0) -> 0 | S35: 45 | T35: =IFERROR(U35/U$20,0) -> 0 | U35: 45 | V35: =IFERROR(W35/W$20,0) -> 0.045 | W35: 45 | X35: =IFERROR(Y35/Y$20,0) -> 0 | Y35: 45 | Z35: =C35+E35+G35+I35+K35+M35+O35+Q35+S35+U35+W35+Y35 -> 555
A36: Conta de energia - 09 | B36: =IFERROR(C36/C$20,0) -> 0.015458446 | C36: 31.02 | D36: =IFERROR(E36/E$20,0) -> 0.012902417 | E36: 35 | F36: =IFERROR(G36/G$20,0) -> 0.012666153 | G36: 35 | H36: =IFERROR(I36/I$20,0) -> 0.013411657 | I36: 35 | J36: =IFERROR(K36/K$20,0) -> 0 | K36: 35 | L36: =IFERROR(M36/M$20,0) -> 0 | M36: 35 | N36: =IFERROR(O36/O$20,0) -> 0 | O36: 35 | P36: =IFERROR(Q36/Q$20,0) -> 0.035 | Q36: 35 | R36: =IFERROR(S36/S$20,0) -> 0 | S36: 35 | T36: =IFERROR(U36/U$20,0) -> 0 | U36: 35 | V36: =IFERROR(W36/W$20,0) -> 0.035 | W36: 35 | X36: =IFERROR(Y36/Y$20,0) -> 0 | Y36: 35 | Z36: =C36+E36+G36+I36+K36+M36+O36+Q36+S36+U36+W36+Y36 -> 416.02
A37: Seguro Residencial | B37: =IFERROR(C37/C$20,0) -> 0 | D37: =IFERROR(E37/E$20,0) -> 0 | F37: =IFERROR(G37/G$20,0) -> 0 | H37: =IFERROR(I37/I$20,0) -> 0 | J37: =IFERROR(K37/K$20,0) -> 0 | L37: =IFERROR(M37/M$20,0) -> 0 | N37: =IFERROR(O37/O$20,0) -> 0 | P37: =IFERROR(Q37/Q$20,0) -> 0 | R37: =IFERROR(S37/S$20,0) -> 0 | T37: =IFERROR(U37/U$20,0) -> 0 | V37: =IFERROR(W37/W$20,0) -> 0 | X37: =IFERROR(Y37/Y$20,0) -> 0 | Z37: =C37+E37+G37+I37+K37+M37+O37+Q37+S37+U37+W37+Y37 -> 0
A38: Conta de gás | B38: =IFERROR(C38/C$20,0) -> 0.014691005 | C38: 29.48 | D38: =IFERROR(E38/E$20,0) -> 0.012902417 | E38: 35 | F38: =IFERROR(G38/G$20,0) -> 0.012666153 | G38: 35 | H38: =IFERROR(I38/I$20,0) -> 0.013411657 | I38: 35 | J38: =IFERROR(K38/K$20,0) -> 0 | K38: 35 | L38: =IFERROR(M38/M$20,0) -> 0 | M38: 35 | N38: =IFERROR(O38/O$20,0) -> 0 | O38: 35 | P38: =IFERROR(Q38/Q$20,0) -> 0.035 | Q38: 35 | R38: =IFERROR(S38/S$20,0) -> 0 | S38: 35 | T38: =IFERROR(U38/U$20,0) -> 0 | U38: 35 | V38: =IFERROR(W38/W$20,0) -> 0.035 | W38: 35 | X38: =IFERROR(Y38/Y$20,0) -> 0 | Y38: 35 | Z38: =C38+E38+G38+I38+K38+M38+O38+Q38+S38+U38+W38+Y38 -> 414.48
A39: Celular+TV+internet | B39: =IFERROR(C39/C$20,0) -> 0.01794017 | C39: 36 | D39: =IFERROR(E39/E$20,0) -> 0.013271058 | E39: 36 | F39: =IFERROR(G39/G$20,0) -> 0.013028043 | G39: 36 | H39: =IFERROR(I39/I$20,0) -> 0.013794848 | I39: 36 | J39: =IFERROR(K39/K$20,0) -> 0 | K39: 36 | L39: =IFERROR(M39/M$20,0) -> 0 | M39: 36 | N39: =IFERROR(O39/O$20,0) -> 0 | O39: 36 | P39: =IFERROR(Q39/Q$20,0) -> 0.036 | Q39: 36 | R39: =IFERROR(S39/S$20,0) -> 0 | S39: 36 | T39: =IFERROR(U39/U$20,0) -> 0 | U39: 36 | V39: =IFERROR(W39/W$20,0) -> 0.036 | W39: 36 | X39: =IFERROR(Y39/Y$20,0) -> 0 | Y39: 36 | Z39: =C39+E39+G39+I39+K39+M39+O39+Q39+S39+U39+W39+Y39 -> 432
A40: Celular | B40: =IFERROR(C40/C$20,0) -> 0 | D40: =IFERROR(E40/E$20,0) -> 0 | F40: =IFERROR(G40/G$20,0) -> 0 | H40: =IFERROR(I40/I$20,0) -> 0 | J40: =IFERROR(K40/K$20,0) -> 0 | L40: =IFERROR(M40/M$20,0) -> 0 | N40: =IFERROR(O40/O$20,0) -> 0 | P40: =IFERROR(Q40/Q$20,0) -> 0 | R40: =IFERROR(S40/S$20,0) -> 0 | T40: =IFERROR(U40/U$20,0) -> 0 | V40: =IFERROR(W40/W$20,0) -> 0 | X40: =IFERROR(Y40/Y$20,0) -> 0 | Z40: =C40+E40+G40+I40+K40+M40+O40+Q40+S40+U40+W40+Y40 -> 0
A41: Amazon Prime / Netflix | B41: =IFERROR(C41/C$20,0) -> 0.0024916902 | C41: 5 | D41: =IFERROR(E41/E$20,0) -> 0.0018432025 | E41: 5 | F41: =IFERROR(G41/G$20,0) -> 0.0018094504 | G41: 5 | H41: =IFERROR(I41/I$20,0) -> 0.0019159511 | I41: 5 | J41: =IFERROR(K41/K$20,0) -> 0 | K41: 5 | L41: =IFERROR(M41/M$20,0) -> 0 | M41: 5 | N41: =IFERROR(O41/O$20,0) -> 0 | O41: 5 | P41: =IFERROR(Q41/Q$20,0) -> 0.005 | Q41: 5 | R41: =IFERROR(S41/S$20,0) -> 0 | S41: 5 | T41: =IFERROR(U41/U$20,0) -> 0 | U41: 5 | V41: =IFERROR(W41/W$20,0) -> 0.005 | W41: 5 | X41: =IFERROR(Y41/Y$20,0) -> 0 | Y41: 5 | Z41: =C41+E41+G41+I41+K41+M41+O41+Q41+S41+U41+W41+Y41 -> 60
A42: Supermercado | B42: =IFERROR(C42/C$20,0) -> 0.19933522 | C42: 400 | D42: =IFERROR(E42/E$20,0) -> 0.1474562 | E42: 400 | F42: =IFERROR(G42/G$20,0) -> 0.14475603 | G42: 400 | H42: =IFERROR(I42/I$20,0) -> 0.15327608 | I42: 400 | J42: =IFERROR(K42/K$20,0) -> 0 | K42: 400 | L42: =IFERROR(M42/M$20,0) -> 0 | M42: 400 | N42: =IFERROR(O42/O$20,0) -> 0 | O42: 400 | P42: =IFERROR(Q42/Q$20,0) -> 0.4 | Q42: 400 | R42: =IFERROR(S42/S$20,0) -> 0 | S42: 400 | T42: =IFERROR(U42/U$20,0) -> 0 | U42: 400 | V42: =IFERROR(W42/W$20,0) -> 0.4 | W42: 400 | X42: =IFERROR(Y42/Y$20,0) -> 0 | Y42: 400 | Z42: =C42+E42+G42+I42+K42+M42+O42+Q42+S42+U42+W42+Y42 -> 4800
A43: Feira | B43: =IFERROR(C43/C$20,0) -> 0 | C43: 0 | D43: =IFERROR(E43/E$20,0) -> 0.018432025 | E43: 50 | F43: =IFERROR(G43/G$20,0) -> 0.018094504 | G43: 50 | H43: =IFERROR(I43/I$20,0) -> 0.019159511 | I43: 50 | J43: =IFERROR(K43/K$20,0) -> 0 | K43: 50 | L43: =IFERROR(M43/M$20,0) -> 0 | M43: 50 | N43: =IFERROR(O43/O$20,0) -> 0 | O43: 50 | P43: =IFERROR(Q43/Q$20,0) -> 0.05 | Q43: 50 | R43: =IFERROR(S43/S$20,0) -> 0 | S43: 50 | T43: =IFERROR(U43/U$20,0) -> 0 | U43: 50 | V43: =IFERROR(W43/W$20,0) -> 0.05 | W43: 50 | X43: =IFERROR(Y43/Y$20,0) -> 0 | Y43: 50 | Z43: =C43+E43+G43+I43+K43+M43+O43+Q43+S43+U43+W43+Y43 -> 550
A44: Açougue | B44: =IFERROR(C44/C$20,0) -> 0.049833804 | C44: 100 | D44: =IFERROR(E44/E$20,0) -> 0.073728098 | E44: 200 | F44: =IFERROR(G44/G$20,0) -> 0.072378016 | G44: 200 | H44: =IFERROR(I44/I$20,0) -> 0.076638042 | I44: 200 | J44: =IFERROR(K44/K$20,0) -> 0 | K44: 200 | L44: =IFERROR(M44/M$20,0) -> 0 | M44: 200 | N44: =IFERROR(O44/O$20,0) -> 0 | O44: 200 | P44: =IFERROR(Q44/Q$20,0) -> 0.2 | Q44: 200 | R44: =IFERROR(S44/S$20,0) -> 0 | S44: 200 | T44: =IFERROR(U44/U$20,0) -> 0 | U44: 200 | V44: =IFERROR(W44/W$20,0) -> 0.2 | W44: 200 | X44: =IFERROR(Y44/Y$20,0) -> 0 | Y44: 200 | Z44: =C44+E44+G44+I44+K44+M44+O44+Q44+S44+U44+W44+Y44 -> 2300
A45: Faxineira | B45: =IFERROR(C45/C$20,0) -> 0 | D45: =IFERROR(E45/E$20,0) -> 0 | F45: =IFERROR(G45/G$20,0) -> 0 | H45: =IFERROR(I45/I$20,0) -> 0 | J45: =IFERROR(K45/K$20,0) -> 0 | L45: =IFERROR(M45/M$20,0) -> 0 | N45: =IFERROR(O45/O$20,0) -> 0 | P45: =IFERROR(Q45/Q$20,0) -> 0 | R45: =IFERROR(S45/S$20,0) -> 0 | T45: =IFERROR(U45/U$20,0) -> 0 | V45: =IFERROR(W45/W$20,0) -> 0 | X45: =IFERROR(Y45/Y$20,0) -> 0 | Z45: =C45+E45+G45+I45+K45+M45+O45+Q45+S45+U45+W45+Y45 -> 0
A46: DIVÍDAS | B46: =IFERROR(C46/C$20,0) -> 0.082629431 | C46: =SUM(C47:C52) -> 165.81 | D46: =IFERROR(E46/E$20,0) -> 0.06112428 | E46: =SUM(E47:E52) -> 165.81 | F46: =IFERROR(G46/G$20,0) -> 0.060004994 | G46: =SUM(G47:G52) -> 165.81 | H46: =IFERROR(I46/I$20,0) -> 0.063536769 | I46: =SUM(I47:I52) -> 165.81 | J46: =IFERROR(K46/K$20,0) -> 0 | K46: =SUM(K47:K52) -> 165.81 | L46: =IFERROR(M46/M$20,0) -> 0 | M46: =SUM(M47:M52) -> 165.81 | N46: =IFERROR(O46/O$20,0) -> 0 | O46: =SUM(O47:O52) -> 165.81 | P46: =IFERROR(Q46/Q$20,0) -> 0.16072 | Q46: =SUM(Q47:Q52) -> 160.72 | R46: =IFERROR(S46/S$20,0) -> 0 | S46: =SUM(S47:S52) -> 104.81 | T46: =IFERROR(U46/U$20,0) -> 0 | U46: =SUM(U47:U52) -> 98.31 | V46: =IFERROR(W46/W$20,0) -> 0.09181 | W46: =SUM(W47:W52) -> 91.81 | X46: =IFERROR(Y46/Y$20,0) -> 0 | Y46: =SUM(Y47:Y52) -> 104.81 | Z46: =C46+E46+G46+I46+K46+M46+O46+Q46+S46+U46+W46+Y46 -> 1721.13
A47: Financiamento carro | B47: =IFERROR(C47/C$20,0) -> 0.05223081 | C47: =104.81 -> 104.81 | D47: =IFERROR(E47/E$20,0) -> 0.03863721 | E47: =104.81 -> 104.81 | F47: =IFERROR(G47/G$20,0) -> 0.037929699 | G47: =104.81 -> 104.81 | H47: =IFERROR(I47/I$20,0) -> 0.040162166 | I47: =104.81 -> 104.81 | J47: =IFERROR(K47/K$20,0) -> 0 | K47: =104.81 -> 104.81 | L47: =IFERROR(M47/M$20,0) -> 0 | M47: =104.81 -> 104.81 | N47: =IFERROR(O47/O$20,0) -> 0 | O47: =104.81 -> 104.81 | P47: =IFERROR(Q47/Q$20,0) -> 0.10481 | Q47: =104.81 -> 104.81 | R47: =IFERROR(S47/S$20,0) -> 0 | S47: =104.81 -> 104.81 | T47: =IFERROR(U47/U$20,0) -> 0 | U47: =S47-6.5 -> 98.31 | V47: =IFERROR(W47/W$20,0) -> 0.09181 | W47: =U47-6.5 -> 91.81 | X47: =IFERROR(Y47/Y$20,0) -> 0 | Y47: =104.81 -> 104.81 | Z47: =C47+E47+G47+I47+K47+M47+O47+Q47+S47+U47+W47+Y47 -> 1238.22
A48: Cheque especial | B48: =IFERROR(C48/C$20,0) -> 0 | D48: =IFERROR(E48/E$20,0) -> 0 | F48: =IFERROR(G48/G$20,0) -> 0 | H48: =IFERROR(I48/I$20,0) -> 0 | J48: =IFERROR(K48/K$20,0) -> 0 | L48: =IFERROR(M48/M$20,0) -> 0 | N48: =IFERROR(O48/O$20,0) -> 0 | P48: =IFERROR(Q48/Q$20,0) -> 0 | R48: =IFERROR(S48/S$20,0) -> 0 | T48: =IFERROR(U48/U$20,0) -> 0 | V48: =IFERROR(W48/W$20,0) -> 0 | X48: =IFERROR(Y48/Y$20,0) -> 0 | Z48: =C48+E48+G48+I48+K48+M48+O48+Q48+S48+U48+W48+Y48 -> 0
A49: Empréstimo consignado | B49: =IFERROR(C49/C$20,0) -> 0 | D49: =IFERROR(E49/E$20,0) -> 0 | F49: =IFERROR(G49/G$20,0) -> 0 | H49: =IFERROR(I49/I$20,0) -> 0 | J49: =IFERROR(K49/K$20,0) -> 0 | L49: =IFERROR(M49/M$20,0) -> 0 | N49: =IFERROR(O49/O$20,0) -> 0 | P49: =IFERROR(Q49/Q$20,0) -> 0 | R49: =IFERROR(S49/S$20,0) -> 0 | T49: =IFERROR(U49/U$20,0) -> 0 | V49: =IFERROR(W49/W$20,0) -> 0 | X49: =IFERROR(Y49/Y$20,0) -> 0 | Z49: =C49+E49+G49+I49+K49+M49+O49+Q49+S49+U49+W49+Y49 -> 0
A50: Cartão de crédito em atraso | B50: =IFERROR(C50/C$20,0) -> 0 | D50: =IFERROR(E50/E$20,0) -> 0 | F50: =IFERROR(G50/G$20,0) -> 0 | H50: =IFERROR(I50/I$20,0) -> 0 | J50: =IFERROR(K50/K$20,0) -> 0 | L50: =IFERROR(M50/M$20,0) -> 0 | N50: =IFERROR(O50/O$20,0) -> 0 | P50: =IFERROR(Q50/Q$20,0) -> 0 | R50: =IFERROR(S50/S$20,0) -> 0 | T50: =IFERROR(U50/U$20,0) -> 0 | V50: =IFERROR(W50/W$20,0) -> 0 | X50: =IFERROR(Y50/Y$20,0) -> 0 | Z50: =C50+E50+G50+I50+K50+M50+O50+Q50+S50+U50+W50+Y50 -> 0
A51: Tributos atrasados | B51: =IFERROR(C51/C$20,0) -> 0 | D51: =IFERROR(E51/E$20,0) -> 0 | F51: =IFERROR(G51/G$20,0) -> 0 | H51: =IFERROR(I51/I$20,0) -> 0 | J51: =IFERROR(K51/K$20,0) -> 0 | L51: =IFERROR(M51/M$20,0) -> 0 | N51: =IFERROR(O51/O$20,0) -> 0 | P51: =IFERROR(Q51/Q$20,0) -> 0 | R51: =IFERROR(S51/S$20,0) -> 0 | T51: =IFERROR(U51/U$20,0) -> 0 | V51: =IFERROR(W51/W$20,0) -> 0 | X51: =IFERROR(Y51/Y$20,0) -> 0 | Z51: =C51+E51+G51+I51+K51+M51+O51+Q51+S51+U51+W51+Y51 -> 0
A52: Outros (IPCA) | B52: =IFERROR(C52/C$20,0) -> 0.030398621 | C52: 61 | D52: =IFERROR(E52/E$20,0) -> 0.02248707 | E52: 61 | F52: =IFERROR(G52/G$20,0) -> 0.022075295 | G52: 61 | H52: =IFERROR(I52/I$20,0) -> 0.023374603 | I52: 61 | J52: =IFERROR(K52/K$20,0) -> 0 | K52: 61 | L52: =IFERROR(M52/M$20,0) -> 0 | M52: 61 | N52: =IFERROR(O52/O$20,0) -> 0 | O52: 61 | P52: =IFERROR(Q52/Q$20,0) -> 0.05591 | Q52: 55.91 | R52: =IFERROR(S52/S$20,0) -> 0 | T52: =IFERROR(U52/U$20,0) -> 0 | V52: =IFERROR(W52/W$20,0) -> 0 | X52: =IFERROR(Y52/Y$20,0) -> 0 | Z52: =C52+E52+G52+I52+K52+M52+O52+Q52+S52+U52+W52+Y52 -> 482.91
A53: SAÚDE | B53: =IFERROR(C53/C$20,0) -> 0 | C53: =SUM(C54:C58) -> 0 | D53: =IFERROR(E53/E$20,0) -> 0.020275227 | E53: =SUM(E54:E58) -> 55 | F53: =IFERROR(G53/G$20,0) -> 0.019903954 | G53: =SUM(G54:G58) -> 55 | H53: =IFERROR(I53/I$20,0) -> 0.021075462 | I53: =SUM(I54:I58) -> 55 | J53: =IFERROR(K53/K$20,0) -> 0 | K53: =SUM(K54:K58) -> 0 | L53: =IFERROR(M53/M$20,0) -> 0 | M53: =SUM(M54:M58) -> 0 | N53: =IFERROR(O53/O$20,0) -> 0 | O53: =SUM(O54:O58) -> 0 | P53: =IFERROR(Q53/Q$20,0) -> 0 | Q53: =SUM(Q54:Q58) -> 0 | R53: =IFERROR(S53/S$20,0) -> 0 | S53: =SUM(S54:S58) -> 0 | T53: =IFERROR(U53/U$20,0) -> 0 | U53: =SUM(U54:U58) -> 0 | V53: =IFERROR(W53/W$20,0) -> 0 | W53: =SUM(W54:W58) -> 0 | X53: =IFERROR(Y53/Y$20,0) -> 0 | Y53: =SUM(Y54:Y58) -> 0 | Z53: =C53+E53+G53+I53+K53+M53+O53+Q53+S53+U53+W53+Y53 -> 165
A54: Plano de Saúde | B54: =IFERROR(C54/C$20,0) -> 0 | D54: =IFERROR(E54/E$20,0) -> 0.020275227 | E54: 55 | F54: =IFERROR(G54/G$20,0) -> 0.019903954 | G54: 55 | H54: =IFERROR(I54/I$20,0) -> 0.021075462 | I54: 55 | J54: =IFERROR(K54/K$20,0) -> 0 | L54: =IFERROR(M54/M$20,0) -> 0 | N54: =IFERROR(O54/O$20,0) -> 0 | P54: =IFERROR(Q54/Q$20,0) -> 0 | R54: =IFERROR(S54/S$20,0) -> 0 | T54: =IFERROR(U54/U$20,0) -> 0 | V54: =IFERROR(W54/W$20,0) -> 0 | X54: =IFERROR(Y54/Y$20,0) -> 0 | Z54: =C54+E54+G54+I54+K54+M54+O54+Q54+S54+U54+W54+Y54 -> 165
A55: Médicos e terapeutas | B55: =IFERROR(C55/C$20,0) -> 0 | D55: =IFERROR(E55/E$20,0) -> 0 | F55: =IFERROR(G55/G$20,0) -> 0 | H55: =IFERROR(I55/I$20,0) -> 0 | J55: =IFERROR(K55/K$20,0) -> 0 | L55: =IFERROR(M55/M$20,0) -> 0 | N55: =IFERROR(O55/O$20,0) -> 0 | P55: =IFERROR(Q55/Q$20,0) -> 0 | R55: =IFERROR(S55/S$20,0) -> 0 | T55: =IFERROR(U55/U$20,0) -> 0 | V55: =IFERROR(W55/W$20,0) -> 0 | X55: =IFERROR(Y55/Y$20,0) -> 0 | Z55: =C55+E55+G55+I55+K55+M55+O55+Q55+S55+U55+W55+Y55 -> 0
A56: Dentista | B56: =IFERROR(C56/C$20,0) -> 0 | D56: =IFERROR(E56/E$20,0) -> 0 | F56: =IFERROR(G56/G$20,0) -> 0 | H56: =IFERROR(I56/I$20,0) -> 0 | J56: =IFERROR(K56/K$20,0) -> 0 | L56: =IFERROR(M56/M$20,0) -> 0 | N56: =IFERROR(O56/O$20,0) -> 0 | P56: =IFERROR(Q56/Q$20,0) -> 0 | R56: =IFERROR(S56/S$20,0) -> 0 | T56: =IFERROR(U56/U$20,0) -> 0 | V56: =IFERROR(W56/W$20,0) -> 0 | X56: =IFERROR(Y56/Y$20,0) -> 0 | Z56: =C56+E56+G56+I56+K56+M56+O56+Q56+S56+U56+W56+Y56 -> 0
A57: Farmácia | B57: =IFERROR(C57/C$20,0) -> 0 | D57: =IFERROR(E57/E$20,0) -> 0 | F57: =IFERROR(G57/G$20,0) -> 0 | H57: =IFERROR(I57/I$20,0) -> 0 | J57: =IFERROR(K57/K$20,0) -> 0 | L57: =IFERROR(M57/M$20,0) -> 0 | N57: =IFERROR(O57/O$20,0) -> 0 | P57: =IFERROR(Q57/Q$20,0) -> 0 | R57: =IFERROR(S57/S$20,0) -> 0 | T57: =IFERROR(U57/U$20,0) -> 0 | V57: =IFERROR(W57/W$20,0) -> 0 | X57: =IFERROR(Y57/Y$20,0) -> 0 | Z57: =C57+E57+G57+I57+K57+M57+O57+Q57+S57+U57+W57+Y57 -> 0
A58: Outros, se houver | B58: =IFERROR(C58/C$20,0) -> 0 | D58: =IFERROR(E58/E$20,0) -> 0 | F58: =IFERROR(G58/G$20,0) -> 0 | H58: =IFERROR(I58/I$20,0) -> 0 | J58: =IFERROR(K58/K$20,0) -> 0 | L58: =IFERROR(M58/M$20,0) -> 0 | N58: =IFERROR(O58/O$20,0) -> 0 | P58: =IFERROR(Q58/Q$20,0) -> 0 | R58: =IFERROR(S58/S$20,0) -> 0 | T58: =IFERROR(U58/U$20,0) -> 0 | V58: =IFERROR(W58/W$20,0) -> 0 | X58: =IFERROR(Y58/Y$20,0) -> 0 | Z58: =C58+E58+G58+I58+K58+M58+O58+Q58+S58+U58+W58+Y58 -> 0
A59: TRANSPORTE | B59: =IFERROR(C59/C$20,0) -> 0.095182566 | C59: =SUM(C60:C70) -> 191 | D59: =IFERROR(E59/E$20,0) -> 0.041656375 | E59: =SUM(E60:E70) -> 113 | F59: =IFERROR(G59/G$20,0) -> 0.040893579 | G59: =SUM(G60:G70) -> 113 | H59: =IFERROR(I59/I$20,0) -> 0.043300494 | I59: =SUM(I60:I70) -> 113 | J59: =IFERROR(K59/K$20,0) -> 0 | K59: =SUM(K60:K70) -> 209 | L59: =IFERROR(M59/M$20,0) -> 0 | M59: =SUM(M60:M70) -> 203 | N59: =IFERROR(O59/O$20,0) -> 0 | O59: =SUM(O60:O70) -> 203 | P59: =IFERROR(Q59/Q$20,0) -> 0.203 | Q59: =SUM(Q60:Q70) -> 203 | R59: =IFERROR(S59/S$20,0) -> 0 | S59: =SUM(S60:S70) -> 209 | T59: =IFERROR(U59/U$20,0) -> 0 | U59: =SUM(U60:U70) -> 113 | V59: =IFERROR(W59/W$20,0) -> 0.313 | W59: =SUM(W60:W70) -> 313 | X59: =IFERROR(Y59/Y$20,0) -> 0 | Y59: =SUM(Y60:Y70) -> 113 | Z59: =C59+E59+G59+I59+K59+M59+O59+Q59+S59+U59+W59+Y59 -> 2096
A60: Licenciamento + multas | B60: =IFERROR(C60/C$20,0) -> 0 | D60: =IFERROR(E60/E$20,0) -> 0 | F60: =IFERROR(G60/G$20,0) -> 0 | H60: =IFERROR(I60/I$20,0) -> 0 | J60: =IFERROR(K60/K$20,0) -> 0 | L60: =IFERROR(M60/M$20,0) -> 0 | N60: =IFERROR(O60/O$20,0) -> 0 | P60: =IFERROR(Q60/Q$20,0) -> 0 | R60: =IFERROR(S60/S$20,0) -> 0 | T60: =IFERROR(U60/U$20,0) -> 0 | V60: =IFERROR(W60/W$20,0) -> 0 | X60: =IFERROR(Y60/Y$20,0) -> 0 | Z60: =C60+E60+G60+I60+K60+M60+O60+Q60+S60+U60+W60+Y60 -> 0
A61: IUC | B61: =IFERROR(C61/C$20,0) -> 0 | D61: =IFERROR(E61/E$20,0) -> 0 | F61: =IFERROR(G61/G$20,0) -> 0 | H61: =IFERROR(I61/I$20,0) -> 0 | J61: =IFERROR(K61/K$20,0) -> 0 | L61: =IFERROR(M61/M$20,0) -> 0 | M61: =270/3 -> 90 | N61: =IFERROR(O61/O$20,0) -> 0 | O61: =270/3 -> 90 | P61: =IFERROR(Q61/Q$20,0) -> 0.09 | Q61: =270/3 -> 90 | R61: =IFERROR(S61/S$20,0) -> 0 | T61: =IFERROR(U61/U$20,0) -> 0 | V61: =IFERROR(W61/W$20,0) -> 0 | X61: =IFERROR(Y61/Y$20,0) -> 0 | Z61: =C61+E61+G61+I61+K61+M61+O61+Q61+S61+U61+W61+Y61 -> 270
A62: Seguro | B62: =IFERROR(C62/C$20,0) -> 0.047840452 | C62: 96 | D62: =IFERROR(E62/E$20,0) -> 0 | F62: =IFERROR(G62/G$20,0) -> 0 | H62: =IFERROR(I62/I$20,0) -> 0 | J62: =IFERROR(K62/K$20,0) -> 0 | K62: 96 | L62: =IFERROR(M62/M$20,0) -> 0 | N62: =IFERROR(O62/O$20,0) -> 0 | P62: =IFERROR(Q62/Q$20,0) -> 0 | R62: =IFERROR(S62/S$20,0) -> 0 | S62: 96 | T62: =IFERROR(U62/U$20,0) -> 0 | V62: =IFERROR(W62/W$20,0) -> 0 | X62: =IFERROR(Y62/Y$20,0) -> 0 | Z62: =C62+E62+G62+I62+K62+M62+O62+Q62+S62+U62+W62+Y62 -> 288
A63: Combustível/metro | B63: =IFERROR(C63/C$20,0) -> 0.019933522 | C63: 40 | D63: =IFERROR(E63/E$20,0) -> 0.01474562 | E63: 40 | F63: =IFERROR(G63/G$20,0) -> 0.014475603 | G63: 40 | H63: =IFERROR(I63/I$20,0) -> 0.015327608 | I63: 40 | J63: =IFERROR(K63/K$20,0) -> 0 | K63: 40 | L63: =IFERROR(M63/M$20,0) -> 0 | M63: 40 | N63: =IFERROR(O63/O$20,0) -> 0 | O63: 40 | P63: =IFERROR(Q63/Q$20,0) -> 0.04 | Q63: 40 | R63: =IFERROR(S63/S$20,0) -> 0 | S63: 40 | T63: =IFERROR(U63/U$20,0) -> 0 | U63: 40 | V63: =IFERROR(W63/W$20,0) -> 0.04 | W63: 40 | X63: =IFERROR(Y63/Y$20,0) -> 0 | Y63: 40 | Z63: =C63+E63+G63+I63+K63+M63+O63+Q63+S63+U63+W63+Y63 -> 480
A64: Cartao Andante | B64: =IFERROR(C64/C$20,0) -> 0.019933522 | C64: 40 | D64: =IFERROR(E64/E$20,0) -> 0.01474562 | E64: 40 | F64: =IFERROR(G64/G$20,0) -> 0.014475603 | G64: 40 | H64: =IFERROR(I64/I$20,0) -> 0.015327608 | I64: 40 | J64: =IFERROR(K64/K$20,0) -> 0 | K64: 40 | L64: =IFERROR(M64/M$20,0) -> 0 | M64: 40 | N64: =IFERROR(O64/O$20,0) -> 0 | O64: 40 | P64: =IFERROR(Q64/Q$20,0) -> 0.04 | Q64: 40 | R64: =IFERROR(S64/S$20,0) -> 0 | S64: 40 | T64: =IFERROR(U64/U$20,0) -> 0 | U64: 40 | V64: =IFERROR(W64/W$20,0) -> 0.04 | W64: 40 | X64: =IFERROR(Y64/Y$20,0) -> 0 | Y64: 40 | Z64: =C64+E64+G64+I64+K64+M64+O64+Q64+S64+U64+W64+Y64 -> 480
A65: Lavagens | B65: =IFERROR(C65/C$20,0) -> 0 | D65: =IFERROR(E65/E$20,0) -> 0.0066355288 | E65: 18 | F65: =IFERROR(G65/G$20,0) -> 0.0065140214 | G65: 18 | H65: =IFERROR(I65/I$20,0) -> 0.0068974238 | I65: 18 | J65: =IFERROR(K65/K$20,0) -> 0 | K65: 18 | L65: =IFERROR(M65/M$20,0) -> 0 | M65: 18 | N65: =IFERROR(O65/O$20,0) -> 0 | O65: 18 | P65: =IFERROR(Q65/Q$20,0) -> 0.018 | Q65: 18 | R65: =IFERROR(S65/S$20,0) -> 0 | S65: 18 | T65: =IFERROR(U65/U$20,0) -> 0 | U65: 18 | V65: =IFERROR(W65/W$20,0) -> 0.018 | W65: 18 | X65: =IFERROR(Y65/Y$20,0) -> 0 | Y65: 18 | Z65: =C65+E65+G65+I65+K65+M65+O65+Q65+S65+U65+W65+Y65 -> 198
A66: Mecânico / Certificacao anual | B66: =IFERROR(C66/C$20,0) -> 0 | D66: =IFERROR(E66/E$20,0) -> 0 | F66: =IFERROR(G66/G$20,0) -> 0 | H66: =IFERROR(I66/I$20,0) -> 0 | J66: =IFERROR(K66/K$20,0) -> 0 | L66: =IFERROR(M66/M$20,0) -> 0 | N66: =IFERROR(O66/O$20,0) -> 0 | P66: =IFERROR(Q66/Q$20,0) -> 0 | R66: =IFERROR(S66/S$20,0) -> 0 | T66: =IFERROR(U66/U$20,0) -> 0 | V66: =IFERROR(W66/W$20,0) -> 0.2 | W66: =200 -> 200 | X66: =IFERROR(Y66/Y$20,0) -> 0 | Z66: =C66+E66+G66+I66+K66+M66+O66+Q66+S66+U66+W66+Y66 -> 200
A67: Multas | B67: =IFERROR(C67/C$20,0) -> 0 | D67: =IFERROR(E67/E$20,0) -> 0 | F67: =IFERROR(G67/G$20,0) -> 0 | H67: =IFERROR(I67/I$20,0) -> 0 | J67: =IFERROR(K67/K$20,0) -> 0 | L67: =IFERROR(M67/M$20,0) -> 0 | N67: =IFERROR(O67/O$20,0) -> 0 | P67: =IFERROR(Q67/Q$20,0) -> 0 | R67: =IFERROR(S67/S$20,0) -> 0 | T67: =IFERROR(U67/U$20,0) -> 0 | V67: =IFERROR(W67/W$20,0) -> 0 | X67: =IFERROR(Y67/Y$20,0) -> 0 | Z67: =C67+E67+G67+I67+K67+M67+O67+Q67+S67+U67+W67+Y67 -> 0
A68: Pedágios + tag | B68: =IFERROR(C68/C$20,0) -> 0.0074750706 | C68: 15 | D68: =IFERROR(E68/E$20,0) -> 0.0055296074 | E68: 15 | F68: =IFERROR(G68/G$20,0) -> 0.0054283512 | G68: 15 | H68: =IFERROR(I68/I$20,0) -> 0.0057478532 | I68: 15 | J68: =IFERROR(K68/K$20,0) -> 0 | K68: 15 | L68: =IFERROR(M68/M$20,0) -> 0 | M68: 15 | N68: =IFERROR(O68/O$20,0) -> 0 | O68: 15 | P68: =IFERROR(Q68/Q$20,0) -> 0.015 | Q68: 15 | R68: =IFERROR(S68/S$20,0) -> 0 | S68: 15 | T68: =IFERROR(U68/U$20,0) -> 0 | U68: 15 | V68: =IFERROR(W68/W$20,0) -> 0.015 | W68: 15 | X68: =IFERROR(Y68/Y$20,0) -> 0 | Y68: 15 | Z68: =C68+E68+G68+I68+K68+M68+O68+Q68+S68+U68+W68+Y68 -> 180
A69: Táxi | B69: =IFERROR(C69/C$20,0) -> 0 | D69: =IFERROR(E69/E$20,0) -> 0 | F69: =IFERROR(G69/G$20,0) -> 0 | H69: =IFERROR(I69/I$20,0) -> 0 | J69: =IFERROR(K69/K$20,0) -> 0 | L69: =IFERROR(M69/M$20,0) -> 0 | N69: =IFERROR(O69/O$20,0) -> 0 | P69: =IFERROR(Q69/Q$20,0) -> 0 | R69: =IFERROR(S69/S$20,0) -> 0 | T69: =IFERROR(U69/U$20,0) -> 0 | V69: =IFERROR(W69/W$20,0) -> 0 | X69: =IFERROR(Y69/Y$20,0) -> 0 | Z69: =C69+E69+G69+I69+K69+M69+O69+Q69+S69+U69+W69+Y69 -> 0
A70: Apps de carro | B70: =IFERROR(C70/C$20,0) -> 0 | D70: =IFERROR(E70/E$20,0) -> 0 | F70: =IFERROR(G70/G$20,0) -> 0 | H70: =IFERROR(I70/I$20,0) -> 0 | J70: =IFERROR(K70/K$20,0) -> 0 | L70: =IFERROR(M70/M$20,0) -> 0 | N70: =IFERROR(O70/O$20,0) -> 0 | P70: =IFERROR(Q70/Q$20,0) -> 0 | R70: =IFERROR(S70/S$20,0) -> 0 | T70: =IFERROR(U70/U$20,0) -> 0 | V70: =IFERROR(W70/W$20,0) -> 0 | X70: =IFERROR(Y70/Y$20,0) -> 0 | Z70: =C70+E70+G70+I70+K70+M70+O70+Q70+S70+U70+W70+Y70 -> 0
A71: DESPESAS PESSOAIS | B71: =IFERROR(C71/C$20,0) -> 0.13179297 | C71: =SUM(C72:C80) -> 264.465 | D71: =IFERROR(E71/E$20,0) -> 0.16016139 | E71: =SUM(E72:E80) -> 434.465 | F71: =IFERROR(G71/G$20,0) -> 0.19341758 | G71: =SUM(G72:G80) -> 534.465 | H71: =IFERROR(I71/I$20,0) -> 0.16648274 | I71: =SUM(I72:I80) -> 434.465 | J71: =IFERROR(K71/K$20,0) -> 0 | K71: =SUM(K72:K80) -> 200 | L71: =IFERROR(M71/M$20,0) -> 0 | M71: =SUM(M72:M80) -> 400 | N71: =IFERROR(O71/O$20,0) -> 0 | O71: =SUM(O72:O80) -> 220 | P71: =IFERROR(Q71/Q$20,0) -> 0.4 | Q71: =SUM(Q72:Q80) -> 400 | R71: =IFERROR(S71/S$20,0) -> 0 | S71: =SUM(S72:S80) -> 100 | T71: =IFERROR(U71/U$20,0) -> 0 | U71: =SUM(U72:U80) -> 520 | V71: =IFERROR(W71/W$20,0) -> 0.1 | W71: =SUM(W72:W80) -> 100 | X71: =IFERROR(Y71/Y$20,0) -> 0 | Y71: =SUM(Y72:Y80) -> 400 | Z71: =C71+E71+G71+I71+K71+M71+O71+Q71+S71+U71+W71+Y71 -> 4007.86
A72: Material escolar | B72: =IFERROR(C72/C$20,0) -> 0 | D72: =IFERROR(E72/E$20,0) -> 0 | F72: =IFERROR(G72/G$20,0) -> 0 | H72: =IFERROR(I72/I$20,0) -> 0 | J72: =IFERROR(K72/K$20,0) -> 0 | L72: =IFERROR(M72/M$20,0) -> 0 | N72: =IFERROR(O72/O$20,0) -> 0 | P72: =IFERROR(Q72/Q$20,0) -> 0 | R72: =IFERROR(S72/S$20,0) -> 0 | T72: =IFERROR(U72/U$20,0) -> 0 | V72: =IFERROR(W72/W$20,0) -> 0 | X72: =IFERROR(Y72/Y$20,0) -> 0 | Z72: =C72+E72+G72+I72+K72+M72+O72+Q72+S72+U72+W72+Y72 -> 0
A73: Higiene Pessoal (unha, depilação etc.) | B73: =IFERROR(C73/C$20,0) -> 0.019933522 | C73: 40 | D73: =IFERROR(E73/E$20,0) -> 0.01474562 | E73: 40 | F73: =IFERROR(G73/G$20,0) -> 0.014475603 | G73: 40 | H73: =IFERROR(I73/I$20,0) -> 0.015327608 | I73: 40 | J73: =IFERROR(K73/K$20,0) -> 0 | K73: 30 | L73: =IFERROR(M73/M$20,0) -> 0 | M73: 30 | N73: =IFERROR(O73/O$20,0) -> 0 | O73: 30 | P73: =IFERROR(Q73/Q$20,0) -> 0.03 | Q73: 30 | R73: =IFERROR(S73/S$20,0) -> 0 | S73: 30 | T73: =IFERROR(U73/U$20,0) -> 0 | U73: 30 | V73: =IFERROR(W73/W$20,0) -> 0.03 | W73: 30 | X73: =IFERROR(Y73/Y$20,0) -> 0 | Y73: 30 | Z73: =C73+E73+G73+I73+K73+M73+O73+Q73+S73+U73+W73+Y73 -> 400
A74: Cosméticos | B74: =IFERROR(C74/C$20,0) -> 0 | D74: =IFERROR(E74/E$20,0) -> 0 | F74: =IFERROR(G74/G$20,0) -> 0.036189008 | G74: 100 | H74: =IFERROR(I74/I$20,0) -> 0 | J74: =IFERROR(K74/K$20,0) -> 0 | L74: =IFERROR(M74/M$20,0) -> 0 | M74: 100 | N74: =IFERROR(O74/O$20,0) -> 0 | P74: =IFERROR(Q74/Q$20,0) -> 0.1 | Q74: 100 | R74: =IFERROR(S74/S$20,0) -> 0 | T74: =IFERROR(U74/U$20,0) -> 0 | U74: 100 | V74: =IFERROR(W74/W$20,0) -> 0 | X74: =IFERROR(Y74/Y$20,0) -> 0 | Y74: 100 | Z74: =C74+E74+G74+I74+K74+M74+O74+Q74+S74+U74+W74+Y74 -> 500
A75: Cabeleireiro | B75: =IFERROR(C75/C$20,0) -> 0 | D75: =IFERROR(E75/E$20,0) -> 0 | F75: =IFERROR(G75/G$20,0) -> 0 | H75: =IFERROR(I75/I$20,0) -> 0 | J75: =IFERROR(K75/K$20,0) -> 0 | L75: =IFERROR(M75/M$20,0) -> 0 | N75: =IFERROR(O75/O$20,0) -> 0 | O75: 120 | P75: =IFERROR(Q75/Q$20,0) -> 0 | R75: =IFERROR(S75/S$20,0) -> 0 | T75: =IFERROR(U75/U$20,0) -> 0 | U75: 120 | V75: =IFERROR(W75/W$20,0) -> 0 | X75: =IFERROR(Y75/Y$20,0) -> 0 | Z75: =C75+E75+G75+I75+K75+M75+O75+Q75+S75+U75+W75+Y75 -> 240
A76: Vestuário | B76: =IFERROR(C76/C$20,0) -> 0 | D76: =IFERROR(E76/E$20,0) -> 0.036864049 | E76: 100 | F76: =IFERROR(G76/G$20,0) -> 0.036189008 | G76: 100 | H76: =IFERROR(I76/I$20,0) -> 0.038319021 | I76: 100 | J76: =IFERROR(K76/K$20,0) -> 0 | K76: 100 | L76: =IFERROR(M76/M$20,0) -> 0 | M76: 200 | N76: =IFERROR(O76/O$20,0) -> 0 | P76: =IFERROR(Q76/Q$20,0) -> 0.2 | Q76: 200 | R76: =IFERROR(S76/S$20,0) -> 0 | T76: =IFERROR(U76/U$20,0) -> 0 | U76: 200 | V76: =IFERROR(W76/W$20,0) -> 0 | X76: =IFERROR(Y76/Y$20,0) -> 0 | Y76: 200 | Z76: =C76+E76+G76+I76+K76+M76+O76+Q76+S76+U76+W76+Y76 -> 1200
A77: Academia Sophia | B77: =IFERROR(C77/C$20,0) -> 0 | D77: =IFERROR(E77/E$20,0) -> 0.012902417 | E77: 35 | F77: =IFERROR(G77/G$20,0) -> 0.012666153 | G77: 35 | H77: =IFERROR(I77/I$20,0) -> 0.013411657 | I77: 35 | J77: =IFERROR(K77/K$20,0) -> 0 | K77: 35 | L77: =IFERROR(M77/M$20,0) -> 0 | M77: 35 | N77: =IFERROR(O77/O$20,0) -> 0 | O77: 35 | P77: =IFERROR(Q77/Q$20,0) -> 0.035 | Q77: 35 | R77: =IFERROR(S77/S$20,0) -> 0 | S77: 35 | T77: =IFERROR(U77/U$20,0) -> 0 | U77: 35 | V77: =IFERROR(W77/W$20,0) -> 0.035 | W77: 35 | X77: =IFERROR(Y77/Y$20,0) -> 0 | Y77: 35 | Z77: =C77+E77+G77+I77+K77+M77+O77+Q77+S77+U77+W77+Y77 -> 385
A78: Seguro de Vida | B78: =IFERROR(C78/C$20,0) -> 0 | D78: =IFERROR(E78/E$20,0) -> 0 | F78: =IFERROR(G78/G$20,0) -> 0 | H78: =IFERROR(I78/I$20,0) -> 0 | J78: =IFERROR(K78/K$20,0) -> 0 | L78: =IFERROR(M78/M$20,0) -> 0 | N78: =IFERROR(O78/O$20,0) -> 0 | P78: =IFERROR(Q78/Q$20,0) -> 0 | R78: =IFERROR(S78/S$20,0) -> 0 | T78: =IFERROR(U78/U$20,0) -> 0 | V78: =IFERROR(W78/W$20,0) -> 0 | X78: =IFERROR(Y78/Y$20,0) -> 0 | Z78: =C78+E78+G78+I78+K78+M78+O78+Q78+S78+U78+W78+Y78 -> 0
A79: Academia Norma | B79: =IFERROR(C79/C$20,0) -> 0 | D79: =IFERROR(E79/E$20,0) -> 0.012902417 | E79: 35 | F79: =IFERROR(G79/G$20,0) -> 0.012666153 | G79: 35 | H79: =IFERROR(I79/I$20,0) -> 0.013411657 | I79: 35 | J79: =IFERROR(K79/K$20,0) -> 0 | K79: 35 | L79: =IFERROR(M79/M$20,0) -> 0 | M79: 35 | N79: =IFERROR(O79/O$20,0) -> 0 | O79: 35 | P79: =IFERROR(Q79/Q$20,0) -> 0.035 | Q79: 35 | R79: =IFERROR(S79/S$20,0) -> 0 | S79: 35 | T79: =IFERROR(U79/U$20,0) -> 0 | U79: 35 | V79: =IFERROR(W79/W$20,0) -> 0.035 | W79: 35 | X79: =IFERROR(Y79/Y$20,0) -> 0 | Y79: 35 | Z79: =C79+E79+G79+I79+K79+M79+O79+Q79+S79+U79+W79+Y79 -> 385
A80: Outros - cama (cartão) | B80: =IFERROR(C80/C$20,0) -> 0.11185945 | C80: =448.93/2 -> 224.465 | D80: =IFERROR(E80/E$20,0) -> 0.082746888 | E80: =448.93/2 -> 224.465 | F80: =IFERROR(G80/G$20,0) -> 0.081231657 | G80: =E80 -> 224.465 | H80: =IFERROR(I80/I$20,0) -> 0.086012791 | I80: =G80 -> 224.465 | J80: =IFERROR(K80/K$20,0) -> 0 | L80: =IFERROR(M80/M$20,0) -> 0 | N80: =IFERROR(O80/O$20,0) -> 0 | P80: =IFERROR(Q80/Q$20,0) -> 0 | R80: =IFERROR(S80/S$20,0) -> 0 | T80: =IFERROR(U80/U$20,0) -> 0 | V80: =IFERROR(W80/W$20,0) -> 0 | X80: =IFERROR(Y80/Y$20,0) -> 0 | Z80: =C80+E80+G80+I80+K80+M80+O80+Q80+S80+U80+W80+Y80 -> 897.86
A81: Total Despesas Essenciais (55%) | B81: =IFERROR(C81/C$20,0) -> 0.98310883 | C81: =C31+C46+C53+C59+C71 -> 1972.775 | D81: =IFERROR(E81/E$20,0) -> 0.84023305 | E81: =E31+E46+E53+E59+E71 -> 2279.275 | F81: =IFERROR(G81/G$20,0) -> 0.86103602 | G81: =G31+G46+G53+G59+G71 -> 2379.275 | H81: =IFERROR(I81/I$20,0) -> 0.87147992 | I81: =I31+I46+I53+I59+I71 -> 2274.275 | J81: =IFERROR(K81/K$20,0) -> 0 | K81: =K31+K46+K53+K59+K71 -> 2080.81 | L81: =IFERROR(M81/M$20,0) -> 0 | M81: =M31+M46+M53+M59+M71 -> 2274.81 | N81: =IFERROR(O81/O$20,0) -> 0 | O81: =O31+O46+O53+O59+O71 -> 2094.81 | P81: =IFERROR(Q81/Q$20,0) -> 2.26972 | Q81: =Q31+Q46+Q53+Q59+Q71 -> 2269.72 | R81: =IFERROR(S81/S$20,0) -> 0 | S81: =S31+S46+S53+S59+S71 -> 1919.81 | T81: =IFERROR(U81/U$20,0) -> 0 | U81: =U31+U46+U53+U59+U71 -> 2237.31 | V81: =IFERROR(W81/W$20,0) -> 2.01081 | W81: =W31+W46+W53+W59+W71 -> 2010.81 | X81: =IFERROR(Y81/Y$20,0) -> 0 | Y81: =Y31+Y46+Y53+Y59+Y71 -> 2123.81 | Z81: =C81+E81+G81+I81+K81+M81+O81+Q81+S81+U81+W81+Y81 -> 25917.49
A83: EDUCAÇÃO | B83: =IFERROR(C83/C$20,0) -> 0 | C83: =SUM(C84:C86) -> 0 | D83: =IFERROR(E83/E$20,0) -> 0.022118429 | E83: =SUM(E84:E86) -> 60 | F83: =IFERROR(G83/G$20,0) -> 0.021713405 | G83: =SUM(G84:G86) -> 60 | H83: =IFERROR(I83/I$20,0) -> 0.022991413 | I83: =SUM(I84:I86) -> 60 | J83: =IFERROR(K83/K$20,0) -> 0 | K83: =SUM(K84:K86) -> 60 | L83: =IFERROR(M83/M$20,0) -> 0 | M83: =SUM(M84:M86) -> 60 | N83: =IFERROR(O83/O$20,0) -> 0 | O83: =SUM(O84:O86) -> 60 | P83: =IFERROR(Q83/Q$20,0) -> 0.06 | Q83: =SUM(Q84:Q86) -> 60 | R83: =IFERROR(S83/S$20,0) -> 0 | S83: =SUM(S84:S86) -> 60 | T83: =IFERROR(U83/U$20,0) -> 0 | U83: =SUM(U84:U86) -> 60 | V83: =IFERROR(W83/W$20,0) -> 0.06 | W83: =SUM(W84:W86) -> 60 | X83: =IFERROR(Y83/Y$20,0) -> 0 | Y83: =SUM(Y84:Y86) -> 60 | Z83: =C83+E83+G83+I83+K83+M83+O83+Q83+S83+U83+W83+Y83 -> 660
A84: Cursos Extra Curriculares | B84: =IFERROR(C84/C$20,0) -> 0 | D84: =IFERROR(E84/E$20,0) -> 0 | F84: =IFERROR(G84/G$20,0) -> 0 | H84: =IFERROR(I84/I$20,0) -> 0 | J84: =IFERROR(K84/K$20,0) -> 0 | L84: =IFERROR(M84/M$20,0) -> 0 | N84: =IFERROR(O84/O$20,0) -> 0 | P84: =IFERROR(Q84/Q$20,0) -> 0 | R84: =IFERROR(S84/S$20,0) -> 0 | T84: =IFERROR(U84/U$20,0) -> 0 | V84: =IFERROR(W84/W$20,0) -> 0 | X84: =IFERROR(Y84/Y$20,0) -> 0 | Z84: =C84+E84+G84+I84+K84+M84+O84+Q84+S84+U84+W84+Y84 -> 0
A85: Ingles | B85: =IFERROR(C85/C$20,0) -> 0 | D85: =IFERROR(E85/E$20,0) -> 0.022118429 | E85: 60 | F85: =IFERROR(G85/G$20,0) -> 0.021713405 | G85: 60 | H85: =IFERROR(I85/I$20,0) -> 0.022991413 | I85: 60 | J85: =IFERROR(K85/K$20,0) -> 0 | K85: 60 | L85: =IFERROR(M85/M$20,0) -> 0 | M85: 60 | N85: =IFERROR(O85/O$20,0) -> 0 | O85: 60 | P85: =IFERROR(Q85/Q$20,0) -> 0.06 | Q85: 60 | R85: =IFERROR(S85/S$20,0) -> 0 | S85: 60 | T85: =IFERROR(U85/U$20,0) -> 0 | U85: 60 | V85: =IFERROR(W85/W$20,0) -> 0.06 | W85: 60 | X85: =IFERROR(Y85/Y$20,0) -> 0 | Y85: 60 | Z85: =C85+E85+G85+I85+K85+M85+O85+Q85+S85+U85+W85+Y85 -> 660
A86: Mestrado IPCA | B86: =IFERROR(C86/C$20,0) -> 0 | D86: =IFERROR(E86/E$20,0) -> 0 | F86: =IFERROR(G86/G$20,0) -> 0 | H86: =IFERROR(I86/I$20,0) -> 0 | J86: =IFERROR(K86/K$20,0) -> 0 | L86: =IFERROR(M86/M$20,0) -> 0 | N86: =IFERROR(O86/O$20,0) -> 0 | P86: =IFERROR(Q86/Q$20,0) -> 0 | R86: =IFERROR(S86/S$20,0) -> 0 | T86: =IFERROR(U86/U$20,0) -> 0 | V86: =IFERROR(W86/W$20,0) -> 0 | X86: =IFERROR(Y86/Y$20,0) -> 0 | Z86: =C86+E86+G86+I86+K86+M86+O86+Q86+S86+U86+W86+Y86 -> 0
A87: Total Despesas Educação (5%) | B87: =IFERROR(C87/C$20,0) -> 0 | C87: =C83 -> 0 | D87: =IFERROR(E87/E$20,0) -> 0.022118429 | E87: =E83 -> 60 | F87: =IFERROR(G87/G$20,0) -> 0.021713405 | G87: =G83 -> 60 | H87: =IFERROR(I87/I$20,0) -> 0.022991413 | I87: =I83 -> 60 | J87: =IFERROR(K87/K$20,0) -> 0 | K87: =K83 -> 60 | L87: =IFERROR(M87/M$20,0) -> 0 | M87: =M83 -> 60 | N87: =IFERROR(O87/O$20,0) -> 0 | O87: =O83 -> 60 | P87: =IFERROR(Q87/Q$20,0) -> 0.06 | Q87: =Q83 -> 60 | R87: =IFERROR(S87/S$20,0) -> 0 | S87: =S83 -> 60 | T87: =IFERROR(U87/U$20,0) -> 0 | U87: =U83 -> 60 | V87: =IFERROR(W87/W$20,0) -> 0.06 | W87: =W83 -> 60 | X87: =IFERROR(Y87/Y$20,0) -> 0 | Y87: =Y83 -> 60 | Z87: =C87+E87+G87+I87+K87+M87+O87+Q87+S87+U87+W87+Y87 -> 660
A89: LAZER | B89: =IFERROR(C89/C$20,0) -> 0 | C89: =SUM(C90:C95) -> 0 | D89: =IFERROR(E89/E$20,0) -> 0.029491239 | E89: =SUM(E90:E95) -> 80 | F89: =IFERROR(G89/G$20,0) -> 0.028951206 | G89: =SUM(G90:G95) -> 80 | H89: =IFERROR(I89/I$20,0) -> 0.030655217 | I89: =SUM(I90:I95) -> 80 | J89: =IFERROR(K89/K$20,0) -> 0 | K89: =SUM(K90:K95) -> 0 | L89: =IFERROR(M89/M$20,0) -> 0 | M89: =SUM(M90:M95) -> 0 | N89: =IFERROR(O89/O$20,0) -> 0 | O89: =SUM(O90:O95) -> 0 | P89: =IFERROR(Q89/Q$20,0) -> 0 | Q89: =SUM(Q90:Q95) -> 0 | R89: =IFERROR(S89/S$20,0) -> 0 | S89: =SUM(S90:S95) -> 0 | T89: =IFERROR(U89/U$20,0) -> 0 | U89: =SUM(U90:U95) -> 0 | V89: =IFERROR(W89/W$20,0) -> 0 | W89: =SUM(W90:W95) -> 0 | X89: =IFERROR(Y89/Y$20,0) -> 0 | Y89: =SUM(Y90:Y95) -> 0 | Z89: =C89+E89+G89+I89+K89+M89+O89+Q89+S89+U89+W89+Y89 -> 240
A90: Restaurantes | B90: =IFERROR(C90/C$20,0) -> 0 | D90: =IFERROR(E90/E$20,0) -> 0.029491239 | E90: 80 | F90: =IFERROR(G90/G$20,0) -> 0.028951206 | G90: =E90 -> 80 | H90: =IFERROR(I90/I$20,0) -> 0.030655217 | I90: 80 | J90: =IFERROR(K90/K$20,0) -> 0 | L90: =IFERROR(M90/M$20,0) -> 0 | N90: =IFERROR(O90/O$20,0) -> 0 | P90: =IFERROR(Q90/Q$20,0) -> 0 | R90: =IFERROR(S90/S$20,0) -> 0 | T90: =IFERROR(U90/U$20,0) -> 0 | V90: =IFERROR(W90/W$20,0) -> 0 | X90: =IFERROR(Y90/Y$20,0) -> 0 | Z90: =C90+E90+G90+I90+K90+M90+O90+Q90+S90+U90+W90+Y90 -> 240
A91: Cafés, bares e boates | B91: =IFERROR(C91/C$20,0) -> 0 | D91: =IFERROR(E91/E$20,0) -> 0 | F91: =IFERROR(G91/G$20,0) -> 0 | H91: =IFERROR(I91/I$20,0) -> 0 | J91: =IFERROR(K91/K$20,0) -> 0 | L91: =IFERROR(M91/M$20,0) -> 0 | N91: =IFERROR(O91/O$20,0) -> 0 | P91: =IFERROR(Q91/Q$20,0) -> 0 | R91: =IFERROR(S91/S$20,0) -> 0 | T91: =IFERROR(U91/U$20,0) -> 0 | V91: =IFERROR(W91/W$20,0) -> 0 | X91: =IFERROR(Y91/Y$20,0) -> 0 | Z91: =C91+E91+G91+I91+K91+M91+O91+Q91+S91+U91+W91+Y91 -> 0
A92: Livraria, jornais e revistas | B92: =IFERROR(C92/C$20,0) -> 0 | D92: =IFERROR(E92/E$20,0) -> 0 | F92: =IFERROR(G92/G$20,0) -> 0 | H92: =IFERROR(I92/I$20,0) -> 0 | J92: =IFERROR(K92/K$20,0) -> 0 | L92: =IFERROR(M92/M$20,0) -> 0 | N92: =IFERROR(O92/O$20,0) -> 0 | P92: =IFERROR(Q92/Q$20,0) -> 0 | R92: =IFERROR(S92/S$20,0) -> 0 | T92: =IFERROR(U92/U$20,0) -> 0 | V92: =IFERROR(W92/W$20,0) -> 0 | X92: =IFERROR(Y92/Y$20,0) -> 0 | Z92: =C92+E92+G92+I92+K92+M92+O92+Q92+S92+U92+W92+Y92 -> 0
A93: Spotify, música e outros | B93: =IFERROR(C93/C$20,0) -> 0 | D93: =IFERROR(E93/E$20,0) -> 0 | F93: =IFERROR(G93/G$20,0) -> 0 | H93: =IFERROR(I93/I$20,0) -> 0 | J93: =IFERROR(K93/K$20,0) -> 0 | L93: =IFERROR(M93/M$20,0) -> 0 | N93: =IFERROR(O93/O$20,0) -> 0 | P93: =IFERROR(Q93/Q$20,0) -> 0 | R93: =IFERROR(S93/S$20,0) -> 0 | T93: =IFERROR(U93/U$20,0) -> 0 | V93: =IFERROR(W93/W$20,0) -> 0 | X93: =IFERROR(Y93/Y$20,0) -> 0 | Z93: =C93+E93+G93+I93+K93+M93+O93+Q93+S93+U93+W93+Y93 -> 0
A94: Passeios | B94: =IFERROR(C94/C$20,0) -> 0 | D94: =IFERROR(E94/E$20,0) -> 0 | F94: =IFERROR(G94/G$20,0) -> 0 | H94: =IFERROR(I94/I$20,0) -> 0 | J94: =IFERROR(K94/K$20,0) -> 0 | L94: =IFERROR(M94/M$20,0) -> 0 | N94: =IFERROR(O94/O$20,0) -> 0 | P94: =IFERROR(Q94/Q$20,0) -> 0 | R94: =IFERROR(S94/S$20,0) -> 0 | T94: =IFERROR(U94/U$20,0) -> 0 | V94: =IFERROR(W94/W$20,0) -> 0 | X94: =IFERROR(Y94/Y$20,0) -> 0 | Z94: =C94+E94+G94+I94+K94+M94+O94+Q94+S94+U94+W94+Y94 -> 0
A95: Outros | B95: =IFERROR(C95/C$20,0) -> 0 | D95: =IFERROR(E95/E$20,0) -> 0 | F95: =IFERROR(G95/G$20,0) -> 0 | H95: =IFERROR(I95/I$20,0) -> 0 | J95: =IFERROR(K95/K$20,0) -> 0 | L95: =IFERROR(M95/M$20,0) -> 0 | N95: =IFERROR(O95/O$20,0) -> 0 | P95: =IFERROR(Q95/Q$20,0) -> 0 | R95: =IFERROR(S95/S$20,0) -> 0 | T95: =IFERROR(U95/U$20,0) -> 0 | V95: =IFERROR(W95/W$20,0) -> 0 | X95: =IFERROR(Y95/Y$20,0) -> 0 | Z95: =C95+E95+G95+I95+K95+M95+O95+Q95+S95+U95+W95+Y95 -> 0
A96: OUTROS | B96: =IFERROR(C96/C$20,0) -> 0.027986664 | C96: =SUM(C97:C110) -> 56.16 | D96: =IFERROR(E96/E$20,0) -> 0.02070285 | E96: =SUM(E97:E110) -> 56.16 | F96: =IFERROR(G96/G$20,0) -> 0.020323747 | G96: =SUM(G97:G110) -> 56.16 | H96: =IFERROR(I96/I$20,0) -> 0.021519962 | I96: =SUM(I97:I110) -> 56.16 | J96: =IFERROR(K96/K$20,0) -> 0 | K96: =SUM(K97:K110) -> 52 | L96: =IFERROR(M96/M$20,0) -> 0 | M96: =SUM(M97:M110) -> 0 | N96: =IFERROR(O96/O$20,0) -> 0 | O96: =SUM(O97:O110) -> 0 | P96: =IFERROR(Q96/Q$20,0) -> 0 | Q96: =SUM(Q97:Q110) -> 0 | R96: =IFERROR(S96/S$20,0) -> 0 | S96: =SUM(S97:S110) -> 0 | T96: =IFERROR(U96/U$20,0) -> 0 | U96: =SUM(U97:U110) -> 0 | V96: =IFERROR(W96/W$20,0) -> 0 | W96: =SUM(W97:W110) -> 0 | X96: =IFERROR(Y96/Y$20,0) -> 0 | Y96: =SUM(Y97:Y110) -> 0 | Z96: =C96+E96+G96+I96+K96+M96+O96+Q96+S96+U96+W96+Y96 -> 276.64
A97: Tarifas Bancárias | B97: =IFERROR(C97/C$20,0) -> 0.0020730863 | C97: 4.16 | D97: =IFERROR(E97/E$20,0) -> 0.0015335444 | E97: 4.16 | F97: =IFERROR(G97/G$20,0) -> 0.0015054627 | G97: 4.16 | H97: =IFERROR(I97/I$20,0) -> 0.0015940713 | I97: 4.16 | J97: =IFERROR(K97/K$20,0) -> 0 | L97: =IFERROR(M97/M$20,0) -> 0 | N97: =IFERROR(O97/O$20,0) -> 0 | P97: =IFERROR(Q97/Q$20,0) -> 0 | R97: =IFERROR(S97/S$20,0) -> 0 | T97: =IFERROR(U97/U$20,0) -> 0 | V97: =IFERROR(W97/W$20,0) -> 0 | X97: =IFERROR(Y97/Y$20,0) -> 0 | Z97: =C97+E97+G97+I97+K97+M97+O97+Q97+S97+U97+W97+Y97 -> 16.64
A98: Ajuda aos pais | B98: =IFERROR(C98/C$20,0) -> 0 | D98: =IFERROR(E98/E$20,0) -> 0 | F98: =IFERROR(G98/G$20,0) -> 0 | H98: =IFERROR(I98/I$20,0) -> 0 | J98: =IFERROR(K98/K$20,0) -> 0 | L98: =IFERROR(M98/M$20,0) -> 0 | N98: =IFERROR(O98/O$20,0) -> 0 | P98: =IFERROR(Q98/Q$20,0) -> 0 | R98: =IFERROR(S98/S$20,0) -> 0 | T98: =IFERROR(U98/U$20,0) -> 0 | V98: =IFERROR(W98/W$20,0) -> 0 | X98: =IFERROR(Y98/Y$20,0) -> 0 | Z98: =C98+E98+G98+I98+K98+M98+O98+Q98+S98+U98+W98+Y98 -> 0
A99: Gorjetas / caixinhas | B99: =IFERROR(C99/C$20,0) -> 0 | D99: =IFERROR(E99/E$20,0) -> 0 | F99: =IFERROR(G99/G$20,0) -> 0 | H99: =IFERROR(I99/I$20,0) -> 0 | J99: =IFERROR(K99/K$20,0) -> 0 | L99: =IFERROR(M99/M$20,0) -> 0 | N99: =IFERROR(O99/O$20,0) -> 0 | P99: =IFERROR(Q99/Q$20,0) -> 0 | R99: =IFERROR(S99/S$20,0) -> 0 | T99: =IFERROR(U99/U$20,0) -> 0 | V99: =IFERROR(W99/W$20,0) -> 0 | X99: =IFERROR(Y99/Y$20,0) -> 0 | Z99: =C99+E99+G99+I99+K99+M99+O99+Q99+S99+U99+W99+Y99 -> 0
A100: Doações e dízimos | B100: =IFERROR(C100/C$20,0) -> 0 | D100: =IFERROR(E100/E$20,0) -> 0 | F100: =IFERROR(G100/G$20,0) -> 0 | H100: =IFERROR(I100/I$20,0) -> 0 | J100: =IFERROR(K100/K$20,0) -> 0 | L100: =IFERROR(M100/M$20,0) -> 0 | N100: =IFERROR(O100/O$20,0) -> 0 | P100: =IFERROR(Q100/Q$20,0) -> 0 | R100: =IFERROR(S100/S$20,0) -> 0 | T100: =IFERROR(U100/U$20,0) -> 0 | V100: =IFERROR(W100/W$20,0) -> 0 | X100: =IFERROR(Y100/Y$20,0) -> 0 | Z100: =C100+E100+G100+I100+K100+M100+O100+Q100+S100+U100+W100+Y100 -> 0
A101: Extras diários | B101: =IFERROR(C101/C$20,0) -> 0 | D101: =IFERROR(E101/E$20,0) -> 0 | F101: =IFERROR(G101/G$20,0) -> 0 | H101: =IFERROR(I101/I$20,0) -> 0 | J101: =IFERROR(K101/K$20,0) -> 0 | L101: =IFERROR(M101/M$20,0) -> 0 | N101: =IFERROR(O101/O$20,0) -> 0 | P101: =IFERROR(Q101/Q$20,0) -> 0 | R101: =IFERROR(S101/S$20,0) -> 0 | T101: =IFERROR(U101/U$20,0) -> 0 | V101: =IFERROR(W101/W$20,0) -> 0 | X101: =IFERROR(Y101/Y$20,0) -> 0 | Z101: =C101+E101+G101+I101+K101+M101+O101+Q101+S101+U101+W101+Y101 -> 0
A102: Manutenção e reparos | B102: =IFERROR(C102/C$20,0) -> 0 | D102: =IFERROR(E102/E$20,0) -> 0 | F102: =IFERROR(G102/G$20,0) -> 0 | H102: =IFERROR(I102/I$20,0) -> 0 | J102: =IFERROR(K102/K$20,0) -> 0 | L102: =IFERROR(M102/M$20,0) -> 0 | N102: =IFERROR(O102/O$20,0) -> 0 | P102: =IFERROR(Q102/Q$20,0) -> 0 | R102: =IFERROR(S102/S$20,0) -> 0 | T102: =IFERROR(U102/U$20,0) -> 0 | V102: =IFERROR(W102/W$20,0) -> 0 | X102: =IFERROR(Y102/Y$20,0) -> 0 | Z102: =C102+E102+G102+I102+K102+M102+O102+Q102+S102+U102+W102+Y102 -> 0
A103: Médicos e terapeutas esporádicos | B103: =IFERROR(C103/C$20,0) -> 0 | D103: =IFERROR(E103/E$20,0) -> 0 | F103: =IFERROR(G103/G$20,0) -> 0 | H103: =IFERROR(I103/I$20,0) -> 0 | J103: =IFERROR(K103/K$20,0) -> 0 | L103: =IFERROR(M103/M$20,0) -> 0 | N103: =IFERROR(O103/O$20,0) -> 0 | P103: =IFERROR(Q103/Q$20,0) -> 0 | R103: =IFERROR(S103/S$20,0) -> 0 | T103: =IFERROR(U103/U$20,0) -> 0 | V103: =IFERROR(W103/W$20,0) -> 0 | X103: =IFERROR(Y103/Y$20,0) -> 0 | Z103: =C103+E103+G103+I103+K103+M103+O103+Q103+S103+U103+W103+Y103 -> 0
A104: Remédios | B104: =IFERROR(C104/C$20,0) -> 0 | D104: =IFERROR(E104/E$20,0) -> 0 | F104: =IFERROR(G104/G$20,0) -> 0 | H104: =IFERROR(I104/I$20,0) -> 0 | J104: =IFERROR(K104/K$20,0) -> 0 | L104: =IFERROR(M104/M$20,0) -> 0 | N104: =IFERROR(O104/O$20,0) -> 0 | P104: =IFERROR(Q104/Q$20,0) -> 0 | R104: =IFERROR(S104/S$20,0) -> 0 | T104: =IFERROR(U104/U$20,0) -> 0 | V104: =IFERROR(W104/W$20,0) -> 0 | X104: =IFERROR(Y104/Y$20,0) -> 0 | Z104: =C104+E104+G104+I104+K104+M104+O104+Q104+S104+U104+W104+Y104 -> 0
A105: Dedetização | B105: =IFERROR(C105/C$20,0) -> 0 | D105: =IFERROR(E105/E$20,0) -> 0 | F105: =IFERROR(G105/G$20,0) -> 0 | H105: =IFERROR(I105/I$20,0) -> 0 | J105: =IFERROR(K105/K$20,0) -> 0 | L105: =IFERROR(M105/M$20,0) -> 0 | N105: =IFERROR(O105/O$20,0) -> 0 | P105: =IFERROR(Q105/Q$20,0) -> 0 | R105: =IFERROR(S105/S$20,0) -> 0 | T105: =IFERROR(U105/U$20,0) -> 0 | V105: =IFERROR(W105/W$20,0) -> 0 | X105: =IFERROR(Y105/Y$20,0) -> 0 | Z105: =C105+E105+G105+I105+K105+M105+O105+Q105+S105+U105+W105+Y105 -> 0
A106: Presente de Natal | B106: =IFERROR(C106/C$20,0) -> 0 | D106: =IFERROR(E106/E$20,0) -> 0 | F106: =IFERROR(G106/G$20,0) -> 0 | H106: =IFERROR(I106/I$20,0) -> 0 | J106: =IFERROR(K106/K$20,0) -> 0 | L106: =IFERROR(M106/M$20,0) -> 0 | N106: =IFERROR(O106/O$20,0) -> 0 | P106: =IFERROR(Q106/Q$20,0) -> 0 | R106: =IFERROR(S106/S$20,0) -> 0 | T106: =IFERROR(U106/U$20,0) -> 0 | V106: =IFERROR(W106/W$20,0) -> 0 | X106: =IFERROR(Y106/Y$20,0) -> 0 | Z106: =C106+E106+G106+I106+K106+M106+O106+Q106+S106+U106+W106+Y106 -> 0
A107: Presentes do Mês | B107: =IFERROR(C107/C$20,0) -> 0 | D107: =IFERROR(E107/E$20,0) -> 0 | F107: =IFERROR(G107/G$20,0) -> 0 | H107: =IFERROR(I107/I$20,0) -> 0 | J107: =IFERROR(K107/K$20,0) -> 0 | L107: =IFERROR(M107/M$20,0) -> 0 | N107: =IFERROR(O107/O$20,0) -> 0 | P107: =IFERROR(Q107/Q$20,0) -> 0 | R107: =IFERROR(S107/S$20,0) -> 0 | T107: =IFERROR(U107/U$20,0) -> 0 | V107: =IFERROR(W107/W$20,0) -> 0 | X107: =IFERROR(Y107/Y$20,0) -> 0 | Z107: =C107+E107+G107+I107+K107+M107+O107+Q107+S107+U107+W107+Y107 -> 0
A108: Utilidades domésticas e decoração | B108: =IFERROR(C108/C$20,0) -> 0 | D108: =IFERROR(E108/E$20,0) -> 0 | F108: =IFERROR(G108/G$20,0) -> 0 | H108: =IFERROR(I108/I$20,0) -> 0 | J108: =IFERROR(K108/K$20,0) -> 0 | L108: =IFERROR(M108/M$20,0) -> 0 | N108: =IFERROR(O108/O$20,0) -> 0 | P108: =IFERROR(Q108/Q$20,0) -> 0 | R108: =IFERROR(S108/S$20,0) -> 0 | T108: =IFERROR(U108/U$20,0) -> 0 | V108: =IFERROR(W108/W$20,0) -> 0 | X108: =IFERROR(Y108/Y$20,0) -> 0 | Z108: =C108+E108+G108+I108+K108+M108+O108+Q108+S108+U108+W108+Y108 -> 0
...

Sheet OBJ_2026
B1: SALARIO BASE | G1: OBJETIVO | H1: ESTRATEGIA | I1: VALOR | J1: ATE | N1: 2024 | O1: 2025 | P1: 2026
F2: 1 | G2: Ganhos liquidos acima 2500 euros/mes | H2: Empreender - Vinhos verdes | N2: ANO 1 | O2: ANO 2 | P2: ANO 3 | Q2: ANO 4 | R2: ANO 5 | S2: ANO 6 | T2: ANO 7 | U2: ANO 8 | V2: ANO 9 | W2: ANO 10 | Z2: TOTAL
B3: Salario | C3: anual | D3: mensal | H3: Buscar trabalho com maior ganho | J3: 45778 | L3: TOTAL DA DIVIDA | M3: 13080 | N3: 1308 | O3: 1308 | P3: 1308 | Q3: 1308 | R3: 1308 | S3: 1308 | T3: 1308 | U3: 1308 | V3: 1308 | W3: 1308
B4: base | C4: 14000 | D4: =C4/12 -> 1166.6667 | H4: Fazer trabalho extra | N4: 2616 | O4: 2616 | P4: 2616 | Q4: 2616 | R4: 2616
B5: comissões | C5: =D5*12 -> 456 | D5: 38 | L5: ATÉ JUL/27 | N5: 4360 | O5: 4360 | P5: 4360
B6: desempenho | C6: =D6*12 -> 192 | D6: 16 | F6: 2 | G6: Quitação carro Nissan Juke | H6: Aplicar bitcoin - 244 por 6 meses | I6: =244*6 -> 1464 | J6: julho | N6: =V18 -> 0.5652 | O6: =V20 -> 1
B7: horario | C7: =D7*12 -> 324 | D7: 27 | H7: Aplicar bitcoin - 244 por 6 meses+premio | I7: =(244*6)+800 -> 2264 | J7: dezembro
C8: =SUM(C4:C7) -> 14972 | D8: 1006
B9: Previdencia | C9: =D9*12 -> 1509 | D9: =D8*12.5% -> 125.75 | F9: 3 | G9: Presente mae ( Portugal) | H9: abril a julho | I9: =(2500+260)/6 -> 460 | J9: julho | N9: jan | O9: fev | P9: mar | Q9: abr | R9: mai | S9: jun | T9: jul | U9: ago | V9: set | W9: out | X9: nov | Y9: dez
B10: Total liquido | C10: =C8-C9 -> 13463 | D10: 880 | L10: total ano | M10: 4360 | N10: 363 | O10: 363 | P10: 363 | Q10: 363 | R10: 363 | S10: 363 | T10: 363 | U10: 363 | V10: 363 | W10: 363 | X10: 363 | Y10: 363 | Z10: =SUM(N10:Y10) -> 4356
B11: VR | D11: 192 | F11: 4 | G11: Férias com mae/filhas | H11: Férias Verão (Ago/Set ) | I11: =900 -> 900 | J11: agosto | L11: total mes | N11: 109 | O11: 109 | P11: 109 | Q11: 109 | R11: 109 | S11: 109 | T11: 109 | U11: 109 | V11: 109 | W11: 109 | X11: 109 | Y11: 109 | Z11: =SUM(N11:Y11) -> 1308
D12: 1072 | L12: total ferias/natal | M12: 4251 | N12: 254 | O12: 254 | P12: 254 | Q12: 254 | R12: 254 | S12: 254 | T12: 254 | U12: 254 | V12: 254 | W12: 254 | X12: 254 | Y12: 254 | Z12: =SUM(N12:Y12) -> 3048
F13: 5 | G13: VIAJAR COM MENINAS | H13: 13 salario | I13: =900 -> 900 | J13: dezembro | R13: a pagar | S13: =SUM(N10:S10) -> 2178
M14: 6540 | R14: sera pago mensal | S14: =SUM(N11:S11) -> 654
B15: PARCELA ACORDO CAN UP | M15: 60 | R15: Bitcoin | S15: =S13-S14 -> 1524
H16: VALOR | I16: VALOR BIT | J16: QTD BIT
B17: 1 parcela | C17: 1890 | D17: 45170 | G17: JANEIRO | L17: 48.65 | M17: ano 1 | N17: 6 meses | O17: 109 | P17: 3.3 | Q17: 29 | R17: dez./24 | S17: 1410.94 | T17: 86 | U17: 115 | V17: 0.2522
B18: 2 parcela | C18: 1890 | D18: 45200 | G18: FEVEREIRO | N18: 6 meses | O18: 109 | P18: 3.3 | Q18: 36 | R18: 45839 | S18: 1459.59 | T18: 50 | V18: 0.5652
B19: 3 parcela | C19: 1260 | D19: 45231 | G19: MARÇO | L19: 1
B20: 4 parcela | C20: 1260 | D20: 45261 | G20: ABRIL | M20: ano 2 | N20: 6 meses | O20: 109 | P20: 3.3 | Q20: 50 | R20: dez./25 | S20: 2140.74 | T20: - | V20: 1
B21: 5 parcela | C21: 1260 | D21: 45292 | G21: MAIO | N21: 6 meses | O21: 109 | P21: 3.3 | Q21: - | R21: mai./26 | S21: 0 | V21: 1
B22: 6 parcela | C22: 1260 | D22: 45323 | G22: JUNHO | J22: =I6+(I6*30%) -> 1903.2
B23: 7 parcela | C23: 1260 | D23: 45352
B24: 8 parcela | C24: 1260 | D24: 45383
B25: 9 parcela | C25: 1260 | D25: 45413 | G25: apoio Municipal / Federal para aluguel | I25: =400 -> 400 | J25: ate julho
B26: 10 parcela | C26: 1260 | D26: 45444
B27: 11 parcela | C27: 1260 | D27: 45474 | G27: O QUE IMPORTA | L27: 46357 | N27: visitar Brasil 3 seman as | P27: =700*3 -> 2100 | Q27: passagens | R27: =6*300 -> 1800 | S27: comprar em Jul/26
B28: 12 parcela | C28: 1260 | D28: 45505 | P28: =P27 -> 2100 | Q28: férias/festa/viagem
B29: 13 parcela | C29: 1260 | D29: 45536 | G29: tempo de qualidade com as meninas
B30: 14 parcela | C30: 1260 | D30: 45566 | G30: cuidar da minha mente e corpo | P30: 2000 | Q30: férias/13 sal
B31: 15 parcela | C31: 1260 | D31: 45597 | G31: viajar mais
B32: 16 parcela | C32: 1260 | D32: 45627 | G32: estar com meus pais
B33: 17 parcela | C33: 1260 | D33: 45658 | G33: Atencao com Sophia na escola | H33: matematica | P33: =((SUM(P27:P28)-SUM(P30:P31))/6) -> 366.66667 | Q33: poupar/mês
B34: 18 parcela | C34: 1260 | D34: 45689 | G34: Atencao com o desenvolvimento da Tina | H34: Ingles
B35: 19 parcela | C35: 1260 | D35: 45717
B36: 20 parcela | C36: 1260 | D36: 45748
B37: 21 parcela | C37: 1400 | D37: 45778
B38: 26600 | C38: 27860
B39: 1260 | C39: recebi a mais ate nov/23

Sheet RESUMO
B2: PLANILHA RESUMO
B4: RESUMO GERAL | C4: Jan | D4: Fev | E4: Mar | F4: Abr | G4: Mai | H4: Jun | I4: Jul | J4: Ago | K4: Set | L4: Out | M4: Nov | N4: Dez | O4: Total
B5: RENDA TOTAL FAMILIAR | C5: ='ORC DOM_2025'!C20 -> 2006.67 | D5: ='ORC DOM_2025'!E20 -> 2712.67 | E5: ='ORC DOM_2025'!G20 -> 2763.27 | F5: ='ORC DOM_2025'!I20 -> 2609.67 | G5: ='ORC DOM_2025'!K20 -> 0 | H5: ='ORC DOM_2025'!M20 -> 0 | I5: ='ORC DOM_2025'!O20 -> 0 | J5: ='ORC DOM_2025'!Q20 -> 1000 | K5: ='ORC DOM_2025'!S20 -> 0 | L5: ='ORC DOM_2025'!U20 -> 0 | M5: ='ORC DOM_2025'!W20 -> 1000 | N5: ='ORC DOM_2025'!Y20 -> 0 | O5: =SUM(C5:N5) -> 12092.28
B6: TOTAL DE DESPESAS | C6: ='ORC DOM_2025'!C113 -> 2028.935 | D6: ='ORC DOM_2025'!E113 -> 2725.435 | E6: ='ORC DOM_2025'!G113 -> 2825.435 | F6: ='ORC DOM_2025'!I113 -> 2720.435 | G6: ='ORC DOM_2025'!K113 -> 2442.81 | H6: ='ORC DOM_2025'!M113 -> 2584.81 | I6: ='ORC DOM_2025'!O113 -> 2404.81 | J6: ='ORC DOM_2025'!Q113 -> 3579.72 | K6: ='ORC DOM_2025'!S113 -> 2229.81 | L6: ='ORC DOM_2025'!U113 -> 2547.31 | M6: ='ORC DOM_2025'!W113 -> 3320.81 | N6: ='ORC DOM_2025'!Y113 -> 2433.81 | O6: =SUM(C6:N6) -> 31844.13
B7: SALDO FINAL | C7: =C5-C6 -> -22.265 | D7: =D5-D6 -> -12.765 | E7: =E5-E6 -> -62.165 | F7: =F5-F6 -> -110.765 | G7: =G5-G6 -> -2442.81 | H7: =H5-H6 -> -2584.81 | I7: =I5-I6 -> -2404.81 | J7: =J5-J6 -> -2579.72 | ... N7: =N5-N6 -> -2433.81 | O7: =SUM(C7:N7) -> -19751.85
B9: RESUMO DAS DESPESAS POR CATEGORIA | C9: Jan | D9: Fev | E9: Mar | F9: Abr | G9: Mai | H9: Jun | I9: Jul | J9: Ago | K9: Set | L9: Out | M9: Nov | N9: Dez | O9: Total por Categoria no ano todo
B10: BOLETO PESSOAL | C10: ='ORC DOM_2025'!C22 -> 0 | D10: ='ORC DOM_2025'!E22 -> 250 | E10: ='ORC DOM_2025'!G22 -> 250 | F10: ='ORC DOM_2025'!I22 -> 250 | G10: ='ORC DOM_2025'!K22 -> 250 | H10: ='ORC DOM_2025'!M22 -> 250 | I10: ='ORC DOM_2025'!O22 -> 250 | J10: ='ORC DOM_2025'!Q22 -> 1250 | K10: ='ORC DOM_2025'!S22 -> 250 | L10: ='ORC DOM_2025'!U22 -> 250 | M10: ='ORC DOM_2025'!W22 -> 1250 | N10: ='ORC DOM_2025'!Y22 -> 250 | O10: =SUM(C10:N10) -> 4750
B11: HABITAÇÃO | C11: ='ORC DOM_2025'!C31 -> 1351.5 | D11: ='ORC DOM_2025'!E31 -> 1511 | E11: ='ORC DOM_2025'!G31 -> 1511 | F11: ='ORC DOM_2025'!I31 -> 1506 | G11: ='ORC DOM_2025'!K31 -> 1506 | H11: ='ORC DOM_2025'!M31 -> 1506 | I11: ='ORC DOM_2025'!O31 -> 1506 | J11: ='ORC DOM_2025'!Q31 -> 1506 | K11: ='ORC DOM_2025'!S31 -> 1506 | L11: ='ORC DOM_2025'!U31 -> 1506 | M11: ='ORC DOM_2025'!W31 -> 1506 | N11: ='ORC DOM_2025'!Y31 -> 1506 | O11: =SUM(C11:N11) -> 17927.5
B12: DÍVIDAS | C12: ='ORC DOM_2025'!C46 -> 165.81 | D12: ='ORC DOM_2025'!E46 -> 165.81 | E12: ='ORC DOM_2025'!G46 -> 165.81 | F12: ='ORC DOM_2025'!I46 -> 165.81 | G12: ='ORC DOM_2025'!K46 -> 165.81 | H12: ='ORC DOM_2025'!M46 -> 165.81 | I12: ='ORC DOM_2025'!O46 -> 165.81 | J12: ='ORC DOM_2025'!Q46 -> 160.72 | K12: ='ORC DOM_2025'!S46 -> 104.81 | L12: ='ORC DOM_2025'!U46 -> 98.31 | M12: ='ORC DOM_2025'!W46 -> 91.81 | N12: ='ORC DOM_2025'!Y46 -> 104.81 | O12: =SUM(C12:N12) -> 1721.13
B13: SAÚDE | C13: ='ORC DOM_2025'!C53 -> 0 | D13: ='ORC DOM_2025'!E53 -> 55 | E13: ='ORC DOM_2025'!G53 -> 55 | F13: ='ORC DOM_2025'!I53 -> 55 | G13: ='ORC DOM_2025'!K53 -> 0 | H13: ='ORC DOM_2025'!M53 -> 0 | I13: ='ORC DOM_2025'!O53 -> 0 | J13: ='ORC DOM_2025'!Q53 -> 0 | K13: ='ORC DOM_2025'!S53 -> 0 | L13: ='ORC DOM_2025'!U53 -> 0 | M13: ='ORC DOM_2025'!W53 -> 0 | N13: ='ORC DOM_2025'!Y53 -> 0 | O13: =SUM(C13:N13) -> 165
B14: TRANSPORTE | C14: ='ORC DOM_2025'!C59 -> 191 | D14: ='ORC DOM_2025'!E59 -> 113 | E14: ='ORC DOM_2025'!G59 -> 113 | F14: ='ORC DOM_2025'!I59 -> 113 | G14: ='ORC DOM_2025'!K59 -> 209 | H14: ='ORC DOM_2025'!M59 -> 203 | I14: ='ORC DOM_2025'!O59 -> 203 | J14: ='ORC DOM_2025'!Q59 -> 203 | K14: ='ORC DOM_2025'!S59 -> 209 | L14: ='ORC DOM_2025'!U59 -> 113 | M14: ='ORC DOM_2025'!W59 -> 313 | N14: ='ORC DOM_2025'!Y59 -> 113 | O14: =SUM(C14:N14) -> 2096
B15: DESPESAS PESSOAIS | C15: ='ORC DOM_2025'!C71 -> 264.465 | D15: ='ORC DOM_2025'!E71 -> 434.465 | E15: ='ORC DOM_2025'!G71 -> 534.465 | F15: ='ORC DOM_2025'!I71 -> 434.465 | G15: ='ORC DOM_2025'!K71 -> 200 | H15: ='ORC DOM_2025'!M71 -> 400 | I15: ='ORC DOM_2025'!O71 -> 220 | J15: ='ORC DOM_2025'!Q71 -> 400 | K15: ='ORC DOM_2025'!S71 -> 100 | L15: ='ORC DOM_2025'!U71 -> 520 | M15: ='ORC DOM_2025'!W71 -> 100 | N15: ='ORC DOM_2025'!Y71 -> 400 | O15: =SUM(C15:N15) -> 4007.86
B16: EDUCAÇÃO | C16: ='ORC DOM_2025'!C83 -> 0 | D16: ='ORC DOM_2025'!E83 -> 60 | E16: ='ORC DOM_2025'!G83 -> 60 | F16: ='ORC DOM_2025'!I83 -> 60 | G16: ='ORC DOM_2025'!K83 -> 60 | H16: ='ORC DOM_2025'!M83 -> 60 | I16: ='ORC DOM_2025'!O83 -> 60 | J16: ='ORC DOM_2025'!Q83 -> 60 | K16: ='ORC DOM_2025'!S83 -> 60 | L16: ='ORC DOM_2025'!U83 -> 60 | M16: ='ORC DOM_2025'!W83 -> 60 | N16: ='ORC DOM_2025'!Y83 -> 60 | O16: =SUM(C16:N16) -> 660
B17: LAZER | C17: ='ORC DOM_2025'!C89 -> 0 | D17: ='ORC DOM_2025'!E89 -> 80 | E17: ='ORC DOM_2025'!G89 -> 80 | F17: ='ORC DOM_2025'!I89 -> 80 | G17: ='ORC DOM_2025'!K89 -> 0 | H17: ='ORC DOM_2025'!M89 -> 0 | I17: ='ORC DOM_2025'!O89 -> 0 | J17: ='ORC DOM_2025'!Q89 -> 0 | K17: ='ORC DOM_2025'!S89 -> 0 | L17: ='ORC DOM_2025'!U89 -> 0 | M17: ='ORC DOM_2025'!W89 -> 0 | N17: ='ORC DOM_2025'!Y89 -> 0 | O17: =SUM(C17:N17) -> 240
B18: OUTROS | C18: ='ORC DOM_2025'!C96 -> 56.16 | D18: ='ORC DOM_2025'!E96 -> 56.16 | E18: ='ORC DOM_2025'!G96 -> 56.16 | F18: ='ORC DOM_2025'!I96 -> 56.16 | G18: ='ORC DOM_2025'!K96 -> 52 | H18: ='ORC DOM_2025'!M96 -> 0 | I18: ='ORC DOM_2025'!O96 -> 0 | J18: ='ORC DOM_2025'!Q96 -> 0 | K18: ='ORC DOM_2025'!S96 -> 0 | L18: ='ORC DOM_2025'!U96 -> 0 | M18: ='ORC DOM_2025'!W96 -> 0 | N18: ='ORC DOM_2025'!Y96 -> 0 | O18: =SUM(C18:N18) -> 276.64
B19: Total no MÊS | C19: =SUM(C10:C18) -> 2028.935 | D19: =SUM(D10:D18) -> 2725.435 | E19: =SUM(E10:E18) -> 2825.435 | F19: =SUM(F10:F18) -> 2720.435 | G19: =SUM(G10:G18) -> 2442.81 | H19: =SUM(H10:H18) -> 2584.81 | I19: =SUM(I10:I18) -> 2404.81 | J19: =SUM(J10:J18) -> 3579.72 | ... O19: =SUM(O10:O18) -> 31844.13
B21: % DE QUANTO A CATEGORIA REPRESENTA COM RELACAO AO SALARIO | C21: Jan | D21: Fev | E21: Mar | F21: Abr | G21: Mai | H21: Jun | I21: Jul | J21: Ago | K21: Set | L21: Out | M21: Nov | N21: Dez | O21: Total
B22: BOLETO PESSOAL | C22: =IFERROR(C10/C$5,0) -> 0 | D22: =IFERROR(D10/D$5,0) -> 0.092160123 | E22: =IFERROR(E10/E$5,0) -> 0.09047252 | F22: =IFERROR(F10/F$5,0) -> 0.095797553 | G22: =IFERROR(G10/G$5,0) -> 0 | H22: =IFERROR(H10/H$5,0) -> 0 | I22: =IFERROR(I10/I$5,0) -> 0 | J22: =IFERROR(J10/J$5,0) -> 1.25 | ... O22: =IFERROR(O10/O$5,0) -> 0.3928126
B23: HABITAÇÃO | C23: =IFERROR(C11/C$5,0) -> 0.67350386 | D23: =IFERROR(D11/D$5,0) -> 0.55701578 | E23: =IFERROR(E11/E$5,0) -> 0.54681591 | F23: =IFERROR(F11/F$5,0) -> 0.57708446 | G23: =IFERROR(G11/G$5,0) -> 0 | H23: =IFERROR(H11/H$5,0) -> 0 | I23: =IFERROR(I11/I$5,0) -> 0 | J23: =IFERROR(J11/J$5,0) -> 1.506 | ... O23: =IFERROR(O11/O$5,0) -> 1.4825575
B24: DÍVIDAS | C24: =IFERROR(C12/C$5,0) -> 0.082629431 | D24: =IFERROR(D12/D$5,0) -> 0.06112428 | E24: =IFERROR(E12/E$5,0) -> 0.060004994 | F24: =IFERROR(F12/F$5,0) -> 0.063536769 | G24: =IFERROR(G12/G$5,0) -> 0 | H24: =IFERROR(H12/H$5,0) -> 0 | I24: =IFERROR(I12/I$5,0) -> 0 | J24: =IFERROR(J12/J$5,0) -> 0.16072 | ... O24: =IFERROR(O12/O$5,0) -> 0.14233296
B25: SAÚDE | C25: =IFERROR(C13/C$5,0) -> 0 | D25: =IFERROR(D13/D$5,0) -> 0.020275227 | E25: =IFERROR(E13/E$5,0) -> 0.019903954 | F25: =IFERROR(F13/F$5,0) -> 0.021075462 | G25: =IFERROR(G13/G$5,0) -> 0 | H25: =IFERROR(H13/H$5,0) -> 0 | I25: =IFERROR(I13/I$5,0) -> 0 | J25: =IFERROR(J13/J$5,0) -> 0 | ... O25: =IFERROR(O13/O$5,0) -> 0.013645069
B26: TRANSPORTE | C26: =IFERROR(C14/C$5,0) -> 0.095182566 | D26: =IFERROR(D14/D$5,0) -> 0.041656375 | E26: =IFERROR(E14/E$5,0) -> 0.040893579 | F26: =IFERROR(F14/F$5,0) -> 0.043300494 | G26: =IFERROR(G14/G$5,0) -> 0 | H26: =IFERROR(H14/H$5,0) -> 0 | I26: =IFERROR(I14/I$5,0) -> 0 | J26: =IFERROR(J14/J$5,0) -> 0.203 | ... O26: =IFERROR(O14/O$5,0) -> 0.17333373
B27: DESPESAS PESSOAIS | C27: =IFERROR(C15/C$5,0) -> 0.13179297 | D27: =IFERROR(D15/D$5,0) -> 0.16016139 | E27: =IFERROR(E15/E$5,0) -> 0.19341758 | F27: =IFERROR(F15/F$5,0) -> 0.16648274 | G27: =IFERROR(G15/G$5,0) -> 0 | H27: =IFERROR(H15/H$5,0) -> 0 | I27: =IFERROR(I15/I$5,0) -> 0 | J27: =IFERROR(J15/J$5,0) -> 0.4 | ... O27: =IFERROR(O15/O$5,0) -> 0.33143956
B28: EDUCAÇÃO | C28: =IFERROR(C16/C$5,0) -> 0 | D28: =IFERROR(D16/D$5,0) -> 0.022118429 | E28: =IFERROR(E16/E$5,0) -> 0.021713405 | F28: =IFERROR(F16/F$5,0) -> 0.022991413 | G28: =IFERROR(G16/G$5,0) -> 0 | H28: =IFERROR(H16/H$5,0) -> 0 | I28: =IFERROR(I16/I$5,0) -> 0 | J28: =IFERROR(J16/J$5,0) -> 0.06 | ... O28: =IFERROR(O16/O$5,0) -> 0.054580278
B29: LAZER | C29: =IFERROR(C17/C$5,0) -> 0 | D29: =IFERROR(D17/D$5,0) -> 0.029491239 | E29: =IFERROR(E17/E$5,0) -> 0.028951206 | F29: =IFERROR(F17/F$5,0) -> 0.030655217 | G29: =IFERROR(G17/G$5,0) -> 0 | H29: =IFERROR(H17/H$5,0) -> 0 | I29: =IFERROR(I17/I$5,0) -> 0 | J29: =IFERROR(J17/J$5,0) -> 0 | ... O29: =IFERROR(O17/O$5,0) -> 0.019847374
B30: OUTROS | C30: =IFERROR(C18/C$5,0) -> 0.027986664 | D30: =IFERROR(D18/D$5,0) -> 0.02070285 | E30: =IFERROR(E18/E$5,0) -> 0.020323747 | F30: =IFERROR(F18/F$5,0) -> 0.021519962 | G30: =IFERROR(G18/G$5,0) -> 0 | H30: =IFERROR(H18/H$5,0) -> 0 | I30: =IFERROR(I18/I$5,0) -> 0 | J30: =IFERROR(J18/J$5,0) -> 0 | ... O30: =IFERROR(O18/O$5,0) -> 0.022877406

Sheet BITCOIN_2025
B2: JANEIRO | C2: FEVEREIRO | D2: MARÇO | E2: ABRIL | F2: MAIO | G2: JUNHO | H2: JULHO | I2: AGOSTO | J2: SETEMBRO | K2: OUTUBRO | L2: NOVEMBRO | M2: DEZEMBRO | P2: TEMPO | Q2: VALOR
A3: Pagamento carro | B3: ='ORC DOM_2025'!C24 | C3: =B3 | D3: =C3 | E3: =D3 | F3: =E3 | G3: =F3 | H3: =G3 | I3: =H3 | J3: =I3 | ... M3: =L3 | O3: 2024 | P3: ANO 1 | Q3: =B12 -> 9853.93 | R3: 1 ano em Portugal | T3: MUDANÇA/ADAPTAÇÃO
A4: Outros | B4: =713/12 -> 59.416667 | C4: =B4 -> 59.416667 | D4: =C4 -> 59.416667 | E4: =D4 -> 59.416667 | F4: =E4 -> 59.416667 | G4: =F4 -> 59.416667 | H4: =G4 -> 59.416667 | I4: =H4 -> 59.416667 | J4: =I4 -> 59.416667 | ... M4: =L4 -> 59.416667 | O4: 2025 | P4: ANO 2 | Q4: =M17 -> 27882.48 | R4: carro pago / visita mae | T4: RECONSTRUÇÃO
A5: Extras | O5: 2026 | P5: ANO 3 | Q5: =Q4+(Q4*N20) -> 69706.199 | R5: viagem Brasil | T5: SOLIDIFICAÇÃO
A6: TOTAL | B6: =SUM(B3:B5) -> 59.416667 | C6: =SUM(C3:C5) -> 59.416667 | D6: =SUM(D3:D5) -> 59.416667 | E6: =SUM(E3:E5) -> 59.416667 | F6: =SUM(F3:F5) -> 59.416667 | G6: =SUM(G3:G5) -> 59.416667 | H6: =SUM(H3:H5) -> 59.416667 | I6: =SUM(I3:I5) -> 59.416667 | ... M6: =SUM(M3:M5) -> 59.416667 | O6: 2027 | P6: ANO 4 | Q6: =Q5+(Q5*N20) -> 174265.5 | T6: REALIZAÇÃO
O7: 2028 | P7: ANO 5 | Q7: =Q6+(Q6*N20) -> 435663.74 | R7: =Q7*0.8% -> 3485.31 | S7: 52 ANOS | T7: APOSENTADORIA
A9: APOSENTADORIA RENDA PASSIVA DE 4000 EUROS AOS 52 ANOS - ATÉ 2028
A11: dolares | B11: 0.1 | C11: 0.1 | D11: 0.1 | E11: 0.1 | F11: 0.1 | G11: 0.1 | H11: 0.1 | I11: 0.1 | J11: 0.1 | K11: 0.1 | L11: 0.1 | M11: 0.1
A12: Acumulado mês | B12: 9853.93 | C12: =B17 -> 10904.681 | D12: =C17 -> 12060.508 | E12: =D17 -> 13331.917 | F12: =E17 -> 14730.467 | G12: =F17 -> 16268.872 | H12: =G17 -> 16337.117 | I12: =H17 -> 18036.188 | J12: =I17 -> 19905.165 | ... M12: =L17 -> 26710.11
A13: Retirada | G13: =(OBJ_2026!S15)+100 -> 1624 | M13: =OBJ_2026!I7+100-800 -> 1564
A14: Aplicaçao mês | B14: =B6 -> 59.416667 | C14: =C6 -> 59.416667 | D14: =D6 -> 59.416667 | E14: =E6 -> 59.416667 | F14: =F6 -> 59.416667 | G14: =G6 -> 59.416667 | H14: =H6 -> 59.416667 | I14: =I6 -> 59.416667 | ... M14: =M6 -> 59.416667
A15: Rendimento | B15: =(B12+B14)*B11 -> 991.33467 | C15: =(C12+C14)*C11 -> 1096.4098 | D15: =(D12+D14)*D11 -> 1211.9924 | E15: =(E12+E14)*E11 -> 1339.1334 | F15: =(F12+F14)*F11 -> 1478.9884 | G15: =(G12+G14)*G11 -> 1632.8289 | H15: =(H12+H14)*H11 -> 1639.6534 | I15: =(I12+I14)*I11 -> 1809.5604 | ... M15: =(M12+M14)*M11 -> 2676.9527
A17: Total mês | B17: =(B12-B13+B14)+B15 -> 10904.681 | C17: =(C12-C13+C14)+C15 -> 12060.508 | D17: =(D12-D13+D14)+D15 -> 13331.917 | E17: =(E12-E13+E14)+E15 -> 14730.467 | F17: =(F12-F13+F14)+F15 -> 16268.872 | G17: =(G12-G13+G14)+G15 -> 16337.117 | H17: =(H12-H13+H14)+H15 -> 18036.188 | I17: =(I12-I13+I14)+I15 -> 19905.165 | ... M17: =(M12-M13+M14)+M15 -> 27882.48
M19: =B17+(B17*N20) -> 27261.703 | N19: MEDIA ANUAL
N20: 1.5

Sheet Carro_25
H4: 2024 | I4: 2025 | J4: 2026
H5: ANO 1 | I5: ANO 2 | J5: ANO 3 | K5: ANO 4 | L5: ANO 5 | M5: ANO 6 | N5: ANO 7 | O5: ANO 8 | P5: ANO 9 | Q5: ANO 10 | T5: TOTAL
F6: TOTAL DA DIVIDA | G6: 13080 | H6: 1308 | I6: 1308 | J6: 1308 | K6: 1308 | L6: 1308 | M6: 1308 | N6: 1308 | O6: 1308 | P6: 1308 | Q6: 1308
H7: 2616 | I7: 2616 | J7: 2616 | K7: 2616 | L7: 2616
F8: ATÉ JUL/27 | H8: 4360 | I8: 4360 | J8: 4360
H9: 0.2522 | I9: 1
H10: jan | I10: fev | J10: mar | K10: abr | L10: mai | M10: jun | N10: jul | O10: ago | P10: set | Q10: out | R10: nov | S10: dez
F11: total ano | G11: 4360 | H11: 363 | I11: 363 | J11: 363 | K11: 363 | L11: 363 | M11: 363 | N11: 363 | O11: 363 | P11: 363 | Q11: 363 | R11: 363 | S11: 363 | T11: =SUM(H11:S11) -> 4356
F12: total mes | H12: 109 | I12: 109 | J12: 109 | K12: 109 | L12: 109 | M12: 109 | N12: 109 | O12: 109 | P12: 109 | Q12: 109 | R12: 109 | S12: 109 | T12: =SUM(H12:S12) -> 1308
F13: total ferias/natal | G13: 4251 | H13: 254 | I13: 254 | J13: 254 | K13: 254 | L13: 254 | M13: 254 | N13: 254 | O13: 254 | P13: 254 | Q13: 254 | R13: 254 | S13: 254 | T13: =SUM(H13:S13) -> 3048
L14: a pagar | M14: =SUM(H11:M11) -> 2178
G15: 6540 | L15: sera pago mensal | M15: =SUM(H12:M12) -> 654
G16: 60 | L16: Bitcoin | M16: =M14-M15 -> 1524
F18: 48.65 | G18: ano 1 | H18: 6 meses | I18: 109 | J18: 3.3 | K18: 29 | L18: dez./24 | M18: 1410.94 | N18: 86 | O18: 115 | P18: 0.2522
H19: 6 meses | I19: 109 | J19: 3.3 | K19: 36 | L19: 45839 | M19: 1459.59 | N19: 50 | P19: 0.5652
F20: 1
G21: ano 2 | H21: 6 meses | I21: 109 | J21: 3.3 | K21: 50 | L21: dez./25 | M21: 2140.74 | N21: - | P21: 1
H22: 6 meses | I22: 109 | J22: 3.3 | K22: - | L22: mai./26 | M22: 0 | P22: 1

Sheet Benefícios
A1: MESES DO ANO | B1: % | C1: 44562 | D1: Meio de Rec./Pag. | E1: % | F1: 44593 | G1: Meio de Rec./Pag. | H1: % | I1: 44621 | J1: Meio de Rec./Pag. | K1: % | L1: 44652 | M1: Meio de Rec./Pag. | N1: % | O1: 44682 | P1: Meio de Rec./Pag. | Q1: % | R1: 44713 | S1: Meio de Rec./Pag. | T1: % | U1: 44743 | V1: Meio de Rec./Pag. | W1: % | X1: 44774 | Y1: Meio de Rec./Pag. | Z1: % | AA1: 44805 | AB1: Meio de Rec./Pag. | AC1: % | AD1: 44835 | AE1: Meio de Rec./Pag. | AF1: % | AG1: 44866 | AH1: Meio de Rec./Pag. | AI1: % | AJ1: 44896 | AK1: Meio de Rec./Pag. | AL1: TOTAL ANO
A2: Benefícios
A3: Vale Refeição | B3: =IFERROR(C3/C$8,0) -> 0 | E3: =IFERROR(F3/F$8,0) -> 0 | H3: =IFERROR(I3/I$8,0) -> 0 | K3: =IFERROR(L3/L$8,0) -> 0 | N3: =IFERROR(O3/O$8,0) -> 0 | Q3: =IFERROR(R3/R$8,0) -> 0 | T3: =IFERROR(U3/U$8,0) -> 0 | W3: =IFERROR(X3/X$8,0) -> 0 | Z3: =IFERROR(AA3/AA$8,0) -> 0 | AC3: =IFERROR(AD3/AD$8,0) -> 0 | AF3: =IFERROR(AG3/AG$8,0) -> 0 | AI3: =IFERROR(AJ3/AJ$8,0) -> 0 | AL3: =C3+F3+I3+L3+O3+R3+U3+X3+AA3+AD3+AG3+AJ3 -> 0
A4: Vale Alimentação | B4: =IFERROR(C4/C$8,0) -> 0 | E4: =IFERROR(F4/F$8,0) -> 0 | H4: =IFERROR(I4/I$8,0) -> 0 | K4: =IFERROR(L4/L$8,0) -> 0 | N4: =IFERROR(O4/O$8,0) -> 0 | Q4: =IFERROR(R4/R$8,0) -> 0 | T4: =IFERROR(U4/U$8,0) -> 0 | W4: =IFERROR(X4/X$8,0) -> 0 | Z4: =IFERROR(AA4/AA$8,0) -> 0 | AC4: =IFERROR(AD4/AD$8,0) -> 0 | AF4: =IFERROR(AG4/AG$8,0) -> 0 | AI4: =IFERROR(AJ4/AJ$8,0) -> 0 | AL4: =C4+F4+I4+L4+O4+R4+U4+X4+AA4+AD4+AG4+AJ4 -> 0
A5: Vale Transporte | B5: =IFERROR(C5/C$8,0) -> 0 | E5: =IFERROR(F5/F$8,0) -> 0 | H5: =IFERROR(I5/I$8,0) -> 0 | K5: =IFERROR(L5/L$8,0) -> 0 | N5: =IFERROR(O5/O$8,0) -> 0 | Q5: =IFERROR(R5/R$8,0) -> 0 | T5: =IFERROR(U5/U$8,0) -> 0 | W5: =IFERROR(X5/X$8,0) -> 0 | Z5: =IFERROR(AA5/AA$8,0) -> 0 | AC5: =IFERROR(AD5/AD$8,0) -> 0 | AF5: =IFERROR(AG5/AG$8,0) -> 0 | AI5: =IFERROR(AJ5/AJ$8,0) -> 0 | AL5: =C5+F5+I5+L5+O5+R5+U5+X5+AA5+AD5+AG5+AJ5 -> 0
A6: Outros | B6: =IFERROR(C6/C$8,0) -> 0 | E6: =IFERROR(F6/F$8,0) -> 0 | H6: =IFERROR(I6/I$8,0) -> 0 | K6: =IFERROR(L6/L$8,0) -> 0 | N6: =IFERROR(O6/O$8,0) -> 0 | Q6: =IFERROR(R6/R$8,0) -> 0 | T6: =IFERROR(U6/U$8,0) -> 0 | W6: =IFERROR(X6/X$8,0) -> 0 | Z6: =IFERROR(AA6/AA$8,0) -> 0 | AC6: =IFERROR(AD6/AD$8,0) -> 0 | AF6: =IFERROR(AG6/AG$8,0) -> 0 | AI6: =IFERROR(AJ6/AJ$8,0) -> 0 | AL6: =C6+F6+I6+L6+O6+R6+U6+X6+AA6+AD6+AG6+AJ6 -> 0
B7: =IFERROR(C7/C$8,0) -> 0 | E7: =IFERROR(F7/F$8,0) -> 0 | H7: =IFERROR(I7/I$8,0) -> 0 | K7: =IFERROR(L7/L$8,0) -> 0 | N7: =IFERROR(O7/O$8,0) -> 0 | Q7: =IFERROR(R7/R$8,0) -> 0 | T7: =IFERROR(U7/U$8,0) -> 0 | W7: =IFERROR(X7/X$8,0) -> 0 | Z7: =IFERROR(AA7/AA$8,0) -> 0 | AC7: =IFERROR(AD7/AD$8,0) -> 0 | AF7: =IFERROR(AG7/AG$8,0) -> 0 | AI7: =IFERROR(AJ7/AJ$8,0) -> 0 | AL7: =C7+F7+I7+L7+O7+R7+U7+X7+AA7+AD7+AG7+AJ7 -> 0
A8: Total Benefícios | B8: 1 | C8: =SUM(C3:C7) -> 0 | E8: 1 | F8: =SUM(F3:F7) -> 0 | H8: 1 | I8: =SUM(I3:I7) -> 0 | K8: 1 | L8: =SUM(L3:L7) -> 0 | N8: 1 | O8: =SUM(O3:O7) -> 0 | Q8: 1 | R8: =SUM(R3:R7) -> 0 | T8: 1 | U8: =SUM(U3:U7) -> 0 | W8: 1 | X8: =SUM(X3:X7) -> 0 | Z8: 1 | AA8: =SUM(AA3:AA7) -> 0 | AC8: 1 | AD8: =SUM(AD3:AD7) -> 0 | AF8: 1 | AG8: =SUM(AG3:AG7) -> 0 | AI8: 1 | AJ8: =SUM(AJ3:AJ7) -> 0 | AL8: =SUM(AL3:AL7) -> 0
A10: Alimentação/Refeição | B10: =IFERROR(C10/C$8,0) -> 0 | C10: =SUM(C11:C17) -> 0 | E10: =IFERROR(F10/F$8,0) -> 0 | F10: =SUM(F11:F17) -> 0 | H10: =IFERROR(I10/I$8,0) -> 0 | I10: =SUM(I11:I17) -> 0 | K10: =IFERROR(L10/L$8,0) -> 0 | L10: =SUM(L11:L17) -> 0 | N10: =IFERROR(O10/O$8,0) -> 0 | O10: =SUM(O11:O17) -> 0 | Q10: =IFERROR(R10/R$8,0) -> 0 | R10: =SUM(R11:R17) -> 0 | T10: =IFERROR(U10/U$8,0) -> 0 | U10: =SUM(U11:U17) -> 0 | W10: =IFERROR(X10/X$8,0) -> 0 | X10: =SUM(X11:X17) -> 0 | Z10: =IFERROR(AA10/AA$8,0) -> 0 | AA10: =SUM(AA11:AA17) -> 0 | AC10: =IFERROR(AD10/AD$8,0) -> 0 | AD10: =SUM(AD11:AD17) -> 0 | AF10: =IFERROR(AG10/AG$8,0) -> 0 | AG10: =SUM(AG11:AG17) -> 0 | AI10: =IFERROR(AJ10/AJ$8,0) -> 0 | AJ10: =SUM(AJ11:AJ17) -> 0 | AL10: =C10+F10+I10+L10+O10+R10+U10+X10+AA10+AD10+AG10+AJ10 -> 0
A11: Supermercado | B11: =IFERROR(C11/C$8,0) -> 0 | E11: =IFERROR(F11/F$8,0) -> 0 | H11: =IFERROR(I11/I$8,0) -> 0 | K11: =IFERROR(L11/L$8,0) -> 0 | N11: =IFERROR(O11/O$8,0) -> 0 | Q11: =IFERROR(R11/R$8,0) -> 0 | T11: =IFERROR(U11/U$8,0) -> 0 | W11: =IFERROR(X11/X$8,0) -> 0 | Z11: =IFERROR(AA11/AA$8,0) -> 0 | AC11: =IFERROR(AD11/AD$8,0) -> 0 | AF11: =IFERROR(AG11/AG$8,0) -> 0 | AI11: =IFERROR(AJ11/AJ$8,0) -> 0 | AL11: =C11+F11+I11+L11+O11+R11+U11+X11+AA11+AD11+AG11+AJ11 -> 0
A12: Restaurante | B12: =IFERROR(C12/C$8,0) -> 0 | E12: =IFERROR(F12/F$8,0) -> 0 | H12: =IFERROR(I12/I$8,0) -> 0 | K12: =IFERROR(L12/L$8,0) -> 0 | N12: =IFERROR(O12/O$8,0) -> 0 | Q12: =IFERROR(R12/R$8,0) -> 0 | T12: =IFERROR(U12/U$8,0) -> 0 | W12: =IFERROR(X12/X$8,0) -> 0 | Z12: =IFERROR(AA12/AA$8,0) -> 0 | AC12: =IFERROR(AD12/AD$8,0) -> 0 | AF12: =IFERROR(AG12/AG$8,0) -> 0 | AI12: =IFERROR(AJ12/AJ$8,0) -> 0 | AL12: =C12+F12+I12+L12+O12+R12+U12+X12+AA12+AD12+AG12+AJ12 -> 0
A13: Bar | B13: =IFERROR(C13/C$8,0) -> 0 | E13: =IFERROR(F13/F$8,0) -> 0 | H13: =IFERROR(I13/I$8,0) -> 0 | K13: =IFERROR(L13/L$8,0) -> 0 | N13: =IFERROR(O13/O$8,0) -> 0 | Q13: =IFERROR(R13/R$8,0) -> 0 | T13: =IFERROR(U13/U$8,0) -> 0 | W13: =IFERROR(X13/X$8,0) -> 0 | Z13: =IFERROR(AA13/AA$8,0) -> 0 | AC13: =IFERROR(AD13/AD$8,0) -> 0 | AF13: =IFERROR(AG13/AG$8,0) -> 0 | AI13: =IFERROR(AJ13/AJ$8,0) -> 0 | AL13: =C13+F13+I13+L13+O13+R13+U13+X13+AA13+AD13+AG13+AJ13 -> 0
A14: Ifood | B14: =IFERROR(C14/C$8,0) -> 0 | E14: =IFERROR(F14/F$8,0) -> 0 | H14: =IFERROR(I14/I$8,0) -> 0 | K14: =IFERROR(L14/L$8,0) -> 0 | N14: =IFERROR(O14/O$8,0) -> 0 | Q14: =IFERROR(R14/R$8,0) -> 0 | T14: =IFERROR(U14/U$8,0) -> 0 | W14: =IFERROR(X14/X$8,0) -> 0 | Z14: =IFERROR(AA14/AA$8,0) -> 0 | AC14: =IFERROR(AD14/AD$8,0) -> 0 | AF14: =IFERROR(AG14/AG$8,0) -> 0 | AI14: =IFERROR(AJ14/AJ$8,0) -> 0 | AL14: =C14+F14+I14+L14+O14+R14+U14+X14+AA14+AD14+AG14+AJ14 -> 0
A15: Outros | B15: =IFERROR(C15/C$8,0) -> 0 | E15: =IFERROR(F15/F$8,0) -> 0 | H15: =IFERROR(I15/I$8,0) -> 0 | K15: =IFERROR(L15/L$8,0) -> 0 | N15: =IFERROR(O15/O$8,0) -> 0 | Q15: =IFERROR(R15/R$8,0) -> 0 | T15: =IFERROR(U15/U$8,0) -> 0 | W15: =IFERROR(X15/X$8,0) -> 0 | Z15: =IFERROR(AA15/AA$8,0) -> 0 | AC15: =IFERROR(AD15/AD$8,0) -> 0 | AF15: =IFERROR(AG15/AG$8,0) -> 0 | AI15: =IFERROR(AJ15/AJ$8,0) -> 0 | AL15: =C15+F15+I15+L15+O15+R15+U15+X15+AA15+AD15+AG15+AJ15 -> 0
B16: =IFERROR(C16/C$8,0) -> 0 | E16: =IFERROR(F16/F$8,0) -> 0 | H16: =IFERROR(I16/I$8,0) -> 0 | K16: =IFERROR(L16/L$8,0) -> 0 | N16: =IFERROR(O16/O$8,0) -> 0 | Q16: =IFERROR(R16/R$8,0) -> 0 | T16: =IFERROR(U16/U$8,0) -> 0 | W16: =IFERROR(X16/X$8,0) -> 0 | Z16: =IFERROR(AA16/AA$8,0) -> 0 | AC16: =IFERROR(AD16/AD$8,0) -> 0 | AF16: =IFERROR(AG16/AG$8,0) -> 0 | AI16: =IFERROR(AJ16/AJ$8,0) -> 0
B17: =IFERROR(C17/C$8,0) -> 0 | E17: =IFERROR(F17/F$8,0) -> 0 | H17: =IFERROR(I17/I$8,0) -> 0 | K17: =IFERROR(L17/L$8,0) -> 0 | N17: =IFERROR(O17/O$8,0) -> 0 | Q17: =IFERROR(R17/R$8,0) -> 0 | T17: =IFERROR(U17/U$8,0) -> 0 | W17: =IFERROR(X17/X$8,0) -> 0 | Z17: =IFERROR(AA17/AA$8,0) -> 0 | AC17: =IFERROR(AD17/AD$8,0) -> 0 | AF17: =IFERROR(AG17/AG$8,0) -> 0 | AI17: =IFERROR(AJ17/AJ$8,0) -> 0 | AL17: =C17+F17+I17+L17+O17+R17+U17+X17+AA17+AD17+AG17+AJ17 -> 0
A18: Transporte | B18: =IFERROR(C18/C$8,0) -> 0 | C18: =SUM(C19:C27) -> 0 | E18: =IFERROR(F18/F$8,0) -> 0 | F18: =SUM(F19:F27) -> 0 | H18: =IFERROR(I18/I$8,0) -> 0 | I18: =SUM(I19:I27) -> 0 | K18: =IFERROR(L18/L$8,0) -> 0 | L18: =SUM(L19:L27) -> 0 | N18: =IFERROR(O18/O$8,0) -> 0 | O18: =SUM(O19:O27) -> 0 | Q18: =IFERROR(R18/R$8,0) -> 0 | R18: =SUM(R19:R27) -> 0 | T18: =IFERROR(U18/U$8,0) -> 0 | U18: =SUM(U19:U27) -> 0 | W18: =IFERROR(X18/X$8,0) -> 0 | X18: =SUM(X19:X27) -> 0 | Z18: =IFERROR(AA18/AA$8,0) -> 0 | AA18: =SUM(AA19:AA27) -> 0 | AC18: =IFERROR(AD18/AD$8,0) -> 0 | AD18: =SUM(AD19:AD27) -> 0 | AF18: =IFERROR(AG18/AG$8,0) -> 0 | AG18: =SUM(AG19:AG27) -> 0 | AI18: =IFERROR(AJ18/AJ$8,0) -> 0 | AJ18: =SUM(AJ19:AJ27) -> 0 | AL18: =C18+F18+I18+L18+O18+R18+U18+X18+AA18+AD18+AG18+AJ18 -> 0
A19: Ônibus | B19: =IFERROR(C19/C$8,0) -> 0 | E19: =IFERROR(F19/F$8,0) -> 0 | H19: =IFERROR(I19/I$8,0) -> 0 | K19: =IFERROR(L19/L$8,0) -> 0 | N19: =IFERROR(O19/O$8,0) -> 0 | Q19: =IFERROR(R19/R$8,0) -> 0 | T19: =IFERROR(U19/U$8,0) -> 0 | W19: =IFERROR(X19/X$8,0) -> 0 | Z19: =IFERROR(AA19/AA$8,0) -> 0 | AC19: =IFERROR(AD19/AD$8,0) -> 0 | AF19: =IFERROR(AG19/AG$8,0) -> 0 | AI19: =IFERROR(AJ19/AJ$8,0) -> 0 | AL19: =C19+F19+I19+L19+O19+R19+U19+X19+AA19+AD19+AG19+AJ19 -> 0
A20: Metrô | B20: =IFERROR(C20/C$8,0) -> 0 | E20: =IFERROR(F20/F$8,0) -> 0 | H20: =IFERROR(I20/I$8,0) -> 0 | K20: =IFERROR(L20/L$8,0) -> 0 | N20: =IFERROR(O20/O$8,0) -> 0 | Q20: =IFERROR(R20/R$8,0) -> 0 | T20: =IFERROR(U20/U$8,0) -> 0 | W20: =IFERROR(X20/X$8,0) -> 0 | Z20: =IFERROR(AA20/AA$8,0) -> 0 | AC20: =IFERROR(AD20/AD$8,0) -> 0 | AF20: =IFERROR(AG20/AG$8,0) -> 0 | AI20: =IFERROR(AJ20/AJ$8,0) -> 0 | AL20: =C20+F20+I20+L20+O20+R20+U20+X20+AA20+AD20+AG20+AJ20 -> 0
A21: Uber | B21: =IFERROR(C21/C$8,0) -> 0 | E21: =IFERROR(F21/F$8,0) -> 0 | H21: =IFERROR(I21/I$8,0) -> 0 | K21: =IFERROR(L21/L$8,0) -> 0 | N21: =IFERROR(O21/O$8,0) -> 0 | Q21: =IFERROR(R21/R$8,0) -> 0 | T21: =IFERROR(U21/U$8,0) -> 0 | W21: =IFERROR(X21/X$8,0) -> 0 | Z21: =IFERROR(AA21/AA$8,0) -> 0 | AC21: =IFERROR(AD21/AD$8,0) -> 0 | AF21: =IFERROR(AG21/AG$8,0) -> 0 | AI21: =IFERROR(AJ21/AJ$8,0) -> 0 | AL21: =C21+F21+I21+L21+O21+R21+U21+X21+AA21+AD21+AG21+AJ21 -> 0
A22: 99 | B22: =IFERROR(C22/C$8,0) -> 0 | E22: =IFERROR(F22/F$8,0) -> 0 | H22: =IFERROR(I22/I$8,0) -> 0 | K22: =IFERROR(L22/L$8,0) -> 0 | N22: =IFERROR(O22/O$8,0) -> 0 | Q22: =IFERROR(R22/R$8,0) -> 0 | T22: =IFERROR(U22/U$8,0) -> 0 | W22: =IFERROR(X22/X$8,0) -> 0 | Z22: =IFERROR(AA22/AA$8,0) -> 0 | AC22: =IFERROR(AD22/AD$8,0) -> 0 | AF22: =IFERROR(AG22/AG$8,0) -> 0 | AI22: =IFERROR(AJ22/AJ$8,0) -> 0 | AL22: =C22+F22+I22+L22+O22+R22+U22+X22+AA22+AD22+AG22+AJ22 -> 0
A23: Táxi | B23: =IFERROR(C23/C$8,0) -> 0 | E23: =IFERROR(F23/F$8,0) -> 0 | H23: =IFERROR(I23/I$8,0) -> 0 | K23: =IFERROR(L23/L$8,0) -> 0 | N23: =IFERROR(O23/O$8,0) -> 0 | Q23: =IFERROR(R23/R$8,0) -> 0 | T23: =IFERROR(U23/U$8,0) -> 0 | W23: =IFERROR(X23/X$8,0) -> 0 | Z23: =IFERROR(AA23/AA$8,0) -> 0 | AC23: =IFERROR(AD23/AD$8,0) -> 0 | AF23: =IFERROR(AG23/AG$8,0) -> 0 | AI23: =IFERROR(AJ23/AJ$8,0) -> 0 | AL23: =C23+F23+I23+L23+O23+R23+U23+X23+AA23+AD23+AG23+AJ23 -> 0
A24: Combustível | B24: =IFERROR(C24/C$8,0) -> 0 | E24: =IFERROR(F24/F$8,0) -> 0 | H24: =IFERROR(I24/I$8,0) -> 0 | K24: =IFERROR(L24/L$8,0) -> 0 | N24: =IFERROR(O24/O$8,0) -> 0 | Q24: =IFERROR(R24/R$8,0) -> 0 | T24: =IFERROR(U24/U$8,0) -> 0 | W24: =IFERROR(X24/X$8,0) -> 0 | Z24: =IFERROR(AA24/AA$8,0) -> 0 | AC24: =IFERROR(AD24/AD$8,0) -> 0 | AF24: =IFERROR(AG24/AG$8,0) -> 0 | AI24: =IFERROR(AJ24/AJ$8,0) -> 0 | AL24: =C24+F24+I24+L24+O24+R24+U24+X24+AA24+AD24+AG24+AJ24 -> 0
A25: Outros | B25: =IFERROR(C25/C$8,0) -> 0 | E25: =IFERROR(F25/F$8,0) -> 0 | H25: =IFERROR(I25/I$8,0) -> 0 | K25: =IFERROR(L25/L$8,0) -> 0 | N25: =IFERROR(O25/O$8,0) -> 0 | Q25: =IFERROR(R25/R$8,0) -> 0 | T25: =IFERROR(U25/U$8,0) -> 0 | W25: =IFERROR(X25/X$8,0) -> 0 | Z25: =IFERROR(AA25/AA$8,0) -> 0 | AC25: =IFERROR(AD25/AD$8,0) -> 0 | AF25: =IFERROR(AG25/AG$8,0) -> 0 | AI25: =IFERROR(AJ25/AJ$8,0) -> 0 | AL25: =C25+F25+I25+L25+O25+R25+U25+X25+AA25+AD25+AG25+AJ25 -> 0
B26: =IFERROR(C26/C$8,0) -> 0 | E26: =IFERROR(F26/F$8,0) -> 0 | H26: =IFERROR(I26/I$8,0) -> 0 | K26: =IFERROR(L26/L$8,0) -> 0 | N26: =IFERROR(O26/O$8,0) -> 0 | Q26: =IFERROR(R26/R$8,0) -> 0 | T26: =IFERROR(U26/U$8,0) -> 0 | W26: =IFERROR(X26/X$8,0) -> 0 | Z26: =IFERROR(AA26/AA$8,0) -> 0 | AC26: =IFERROR(AD26/AD$8,0) -> 0 | AF26: =IFERROR(AG26/AG$8,0) -> 0 | AI26: =IFERROR(AJ26/AJ$8,0) -> 0 | AL26: =C26+F26+I26+L26+O26+R26+U26+X26+AA26+AD26+AG26+AJ26 -> 0
B27: =IFERROR(C27/C$8,0) -> 0 | E27: =IFERROR(F27/F$8,0) -> 0 | H27: =IFERROR(I27/I$8,0) -> 0 | K27: =IFERROR(L27/L$8,0) -> 0 | N27: =IFERROR(O27/O$8,0) -> 0 | Q27: =IFERROR(R27/R$8,0) -> 0 | T27: =IFERROR(U27/U$8,0) -> 0 | W27: =IFERROR(X27/X$8,0) -> 0 | Z27: =IFERROR(AA27/AA$8,0) -> 0 | AC27: =IFERROR(AD27/AD$8,0) -> 0 | AF27: =IFERROR(AG27/AG$8,0) -> 0 | AI27: =IFERROR(AJ27/AJ$8,0) -> 0 | AL27: =C27+F27+I27+L27+O27+R27+U27+X27+AA27+AD27+AG27+AJ27 -> 0
A28: Total Gastos Benefícios | B28: =IFERROR(C28/C$8,0) -> 0 | C28: =C10+C18 -> 0 | E28: =IFERROR(F28/F$8,0) -> 0 | F28: =F10+F18 -> 0 | H28: =IFERROR(I28/I$8,0) -> 0 | I28: =I10+I18 -> 0 | K28: =IFERROR(L28/L$8,0) -> 0 | L28: =L10+L18 -> 0 | N28: =IFERROR(O28/O$8,0) -> 0 | O28: =O10+O18 -> 0 | Q28: =IFERROR(R28/R$8,0) -> 0 | R28: =R10+R18 -> 0 | T28: =IFERROR(U28/U$8,0) -> 0 | U28: =U10+U18 -> 0 | W28: =IFERROR(X28/X$8,0) -> 0 | X28: =X10+X18 -> 0 | Z28: =IFERROR(AA28/AA$8,0) -> 0 | AA28: =AA10+AA18 -> 0 | AC28: =IFERROR(AD28/AD$8,0) -> 0 | AD28: =AD10+AD18 -> 0 | AF28: =IFERROR(AG28/AG$8,0) -> 0 | AG28: =AG10+AG18 -> 0 | AI28: =IFERROR(AJ28/AJ$8,0) -> 0 | AJ28: =AJ10+AJ18 -> 0 | AL28: =C28+F28+I28+L28+O28+R28+U28+X28+AA28+AD28+AG28+AJ28 -> 0
A30: Saldo Disponível no mês | B30: =C8-C28 -> 0 | E30: =F8-F28 -> 0 | H30: =I8-I28 -> 0 | K30: =L8-L28 -> 0 | N30: =O8-O28 -> 0 | Q30: =R8-R28 -> 0 | T30: =U8-U28 -> 0 | W30: =X8-X28 -> 0 | Z30: =AA8-AA28 -> 0 | AC30: =AD8-AD28 -> 0 | AF30: =AG8-AG28 -> 0 | AI30: =AJ8-AJ28 -> 0 | AL30: =SUM(B30:AJ30) -> 0

Sheet Como Gasto

Sheet Rec x Desp

Sheet Boleto Pessoal

Sheet Habitação

Sheet Dívidas

Sheet Saúde

Sheet Transporte

Sheet Desp Pessoais

Sheet Educação

Sheet Lazer

Sheet Outros

Sheet Dados
B4: PLANILHA SUPORTE PARA OS GRAFICOS
C7: Jan | D7: Fev | E7: Mar | F7: Abr | G7: Mai | H7: Jun | I7: Jul | J7: Ago | K7: Set | L7: Out | M7: Nov | N7: Dez | O7: Total
B8: BOLETO PESSOAL | C8: ='ORC DOM_2025'!C22 -> 0 | D8: ='ORC DOM_2025'!E22 -> 250 | E8: ='ORC DOM_2025'!G22 -> 250 | F8: ='ORC DOM_2025'!I22 -> 250 | G8: ='ORC DOM_2025'!K22 -> 250 | H8: ='ORC DOM_2025'!M22 -> 250 | I8: ='ORC DOM_2025'!O22 -> 250 | J8: ='ORC DOM_2025'!Q22 -> 1250 | K8: ='ORC DOM_2025'!S22 -> 250 | L8: ='ORC DOM_2025'!U22 -> 250 | M8: ='ORC DOM_2025'!W22 -> 1250 | N8: ='ORC DOM_2025'!Y22 -> 250 | O8: =SUM(C8:N8) -> 4750
B9: ='ORC DOM_2025'!A31 -> HABITAÇÃO | C9: ='ORC DOM_2025'!C31 -> 1351.5 | D9: ='ORC DOM_2025'!E31 -> 1511 | E9: ='ORC DOM_2025'!G31 -> 1511 | F9: ='ORC DOM_2025'!I31 -> 1506 | G9: ='ORC DOM_2025'!K31 -> 1506 | H9: ='ORC DOM_2025'!M31 -> 1506 | I9: ='ORC DOM_2025'!O31 -> 1506 | J9: ='ORC DOM_2025'!Q31 -> 1506 | K9: ='ORC DOM_2025'!S31 -> 1506 | L9: ='ORC DOM_2025'!U31 -> 1506 | M9: ='ORC DOM_2025'!W31 -> 1506 | N9: ='ORC DOM_2025'!Y31 -> 1506 | O9: =SUM(C9:N9) -> 17927.5
B10: DÍVIDAS | C10: ='ORC DOM_2025'!C46 -> 165.81 | D10: ='ORC DOM_2025'!E46 -> 165.81 | E10: ='ORC DOM_2025'!G46 -> 165.81 | F10: ='ORC DOM_2025'!I46 -> 165.81 | G10: ='ORC DOM_2025'!K46 -> 165.81 | H10: ='ORC DOM_2025'!M46 -> 165.81 | I10: ='ORC DOM_2025'!O46 -> 165.81 | J10: ='ORC DOM_2025'!Q46 -> 160.72 | K10: ='ORC DOM_2025'!S46 -> 104.81 | L10: ='ORC DOM_2025'!U46 -> 98.31 | M10: ='ORC DOM_2025'!W46 -> 91.81 | N10: ='ORC DOM_2025'!Y46 -> 104.81 | O10: =SUM(C10:N10) -> 1721.13
B11: ='ORC DOM_2025'!A53 -> SAÚDE | C11: ='ORC DOM_2025'!C53 -> 0 | D11: ='ORC DOM_2025'!E53 -> 55 | E11: ='ORC DOM_2025'!G53 -> 55 | F11: ='ORC DOM_2025'!I53 -> 55 | G11: ='ORC DOM_2025'!K53 -> 0 | H11: ='ORC DOM_2025'!M53 -> 0 | I11: ='ORC DOM_2025'!O53 -> 0 | J11: ='ORC DOM_2025'!Q53 -> 0 | K11: ='ORC DOM_2025'!S53 -> 0 | L11: ='ORC DOM_2025'!U53 -> 0 | M11: ='ORC DOM_2025'!W53 -> 0 | N11: ='ORC DOM_2025'!Y53 -> 0 | O11: =SUM(C11:N11) -> 165
B12: ='ORC DOM_2025'!A59 -> TRANSPORTE | C12: ='ORC DOM_2025'!C59 -> 191 | D12: ='ORC DOM_2025'!E59 -> 113 | E12: ='ORC DOM_2025'!G59 -> 113 | F12: ='ORC DOM_2025'!I59 -> 113 | G12: ='ORC DOM_2025'!K59 -> 209 | H12: ='ORC DOM_2025'!M59 -> 203 | I12: ='ORC DOM_2025'!O59 -> 203 | J12: ='ORC DOM_2025'!Q59 -> 203 | K12: ='ORC DOM_2025'!S59 -> 209 | L12: ='ORC DOM_2025'!U59 -> 113 | M12: ='ORC DOM_2025'!W59 -> 313 | N12: ='ORC DOM_2025'!Y59 -> 113 | O12: =SUM(C12:N12) -> 2096
B13: ='ORC DOM_2025'!A71 -> DESPESAS PESSOAIS | C13: ='ORC DOM_2025'!C71 -> 264.465 | D13: ='ORC DOM_2025'!E71 -> 434.465 | E13: ='ORC DOM_2025'!G71 -> 534.465 | F13: ='ORC DOM_2025'!I71 -> 434.465 | G13: ='ORC DOM_2025'!K71 -> 200 | H13: ='ORC DOM_2025'!M71 -> 400 | I13: ='ORC DOM_2025'!O71 -> 220 | J13: ='ORC DOM_2025'!Q71 -> 400 | K13: ='ORC DOM_2025'!S71 -> 100 | L13: ='ORC DOM_2025'!U71 -> 520 | M13: ='ORC DOM_2025'!W71 -> 100 | N13: ='ORC DOM_2025'!Y71 -> 400 | O13: =SUM(C13:N13) -> 4007.86
B14: ='ORC DOM_2025'!A83 -> EDUCAÇÃO | C14: ='ORC DOM_2025'!C83 -> 0 | D14: ='ORC DOM_2025'!E83 -> 60 | E14: ='ORC DOM_2025'!G83 -> 60 | F14: ='ORC DOM_2025'!I83 -> 60 | G14: ='ORC DOM_2025'!K83 -> 60 | H14: ='ORC DOM_2025'!M83 -> 60 | I14: ='ORC DOM_2025'!O83 -> 60 | J14: ='ORC DOM_2025'!Q83 -> 60 | K14: ='ORC DOM_2025'!S83 -> 60 | L14: ='ORC DOM_2025'!U83 -> 60 | M14: ='ORC DOM_2025'!W83 -> 60 | N14: ='ORC DOM_2025'!Y83 -> 60 | O14: =SUM(C14:N14) -> 660
B15: ='ORC DOM_2025'!A89 -> LAZER | C15: ='ORC DOM_2025'!C89 -> 0 | D15: ='ORC DOM_2025'!E89 -> 80 | E15: ='ORC DOM_2025'!G89 -> 80 | F15: ='ORC DOM_2025'!I89 -> 80 | G15: ='ORC DOM_2025'!K89 -> 0 | H15: ='ORC DOM_2025'!M89 -> 0 | I15: ='ORC DOM_2025'!O89 -> 0 | J15: ='ORC DOM_2025'!Q89 -> 0 | K15: ='ORC DOM_2025'!S89 -> 0 | L15: ='ORC DOM_2025'!U89 -> 0 | M15: ='ORC DOM_2025'!W89 -> 0 | N15: ='ORC DOM_2025'!Y89 -> 0 | O15: =SUM(C15:N15) -> 240
B16: ='ORC DOM_2025'!A96 -> OUTROS | C16: ='ORC DOM_2025'!C96 -> 56.16 | D16: ='ORC DOM_2025'!E96 -> 56.16 | E16: ='ORC DOM_2025'!G96 -> 56.16 | F16: ='ORC DOM_2025'!I96 -> 56.16 | G16: ='ORC DOM_2025'!K96 -> 52 | H16: ='ORC DOM_2025'!M96 -> 0 | I16: ='ORC DOM_2025'!O96 -> 0 | J16: ='ORC DOM_2025'!Q96 -> 0 | K16: ='ORC DOM_2025'!S96 -> 0 | L16: ='ORC DOM_2025'!U96 -> 0 | M16: ='ORC DOM_2025'!W96 -> 0 | N16: ='ORC DOM_2025'!Y96 -> 0 | O16: =SUM(C16:N16) -> 276.64
C20: 1o Trim | D20: 2o Trim | E20: 3o Trim | F20: 4o Trim | G20: TOTAL
B21: BOLETO PESSOAL | C21: =SUM(C8:E8) -> 500 | D21: =SUM(F8:H8) -> 750 | E21: =SUM(I8:K8) -> 1750 | F21: =SUM(L8:N8) -> 1750 | G21: =SUM(C21:F21) -> 4750
B22: HABITAÇÃO | C22: =SUM(C9:E9) -> 4373.5 | D22: =SUM(F9:H9) -> 4518 | E22: =SUM(I9:K9) -> 4518 | F22: =SUM(L9:N9) -> 4518 | G22: =SUM(C22:F22) -> 17927.5
B23: DÍVIDAS | C23: =SUM(C10:E10) -> 497.43 | D23: =SUM(F10:H10) -> 497.43 | E23: =SUM(I10:K10) -> 431.34 | F23: =SUM(L10:N10) -> 294.93 | G23: =SUM(C23:F23) -> 1721.13
B24: SAÚDE | C24: =SUM(C11:E11) -> 110 | D24: =SUM(F11:H11) -> 55 | E24: =SUM(I11:K11) -> 0 | F24: =SUM(L11:N11) -> 0 | G24: =SUM(C24:F24) -> 165
B25: TRANSPORTE | C25: =SUM(C12:E12) -> 417 | D25: =SUM(F12:H12) -> 525 | E25: =SUM(I12:K12) -> 615 | F25: =SUM(L12:N12) -> 539 | G25: =SUM(C25:F25) -> 2096
B26: DESPESAS PESSOAIS | C26: =SUM(C13:E13) -> 1233.395 | D26: =SUM(F13:H13) -> 1034.465 | E26: =SUM(I13:K13) -> 720 | F26: =SUM(L13:N13) -> 1020 | G26: =SUM(C26:F26) -> 4007.86
B27: EDUCAÇÃO | C27: =SUM(C14:E14) -> 120 | D27: =SUM(F14:H14) -> 180 | E27: =SUM(I14:K14) -> 180 | F27: =SUM(L14:N14) -> 180 | G27: =SUM(C27:F27) -> 660
B28: LAZER | C28: =SUM(C15:E15) -> 160 | D28: =SUM(F15:H15) -> 80 | E28: =SUM(I15:K15) -> 0 | F28: =SUM(L15:N15) -> 0 | G28: =SUM(C28:F28) -> 240
B29: OUTROS | C29: =SUM(C16:E16) -> 168.48 | D29: =SUM(F16:H16) -> 108.16 | E29: =SUM(I16:K16) -> 0 | F29: =SUM(L16:N16) -> 0 | G29: =SUM(C29:F29) -> 276.64
B30: TOTAL | C30: =SUM(C21:C29) -> 7579.805 | D30: =SUM(D21:D29) -> 7748.055 | E30: =SUM(E21:E29) -> 8214.34 | F30: =SUM(F21:F29) -> 8301.93 | G30: =SUM(G21:G29) -> 31844.13
C33: 1o Trim | D33: 2o Trim | E33: 3o Trim | F33: 4o Trim | G33: TOTAL
B34: BOLETO PESSOAL | C34: =C21/C$30 -> 0.065964758 | D34: =D21/D$30 -> 0.096798487 | E34: =E21/E$30 -> 0.21304207 | F34: =F21/F$30 -> 0.21079436 | G34: =G21/G$30 -> 0.14916407
B35: HABITAÇÃO | C35: =C22/C$30 -> 0.57699374 | D35: =D22/D$30 -> 0.58311408 | E35: =E22/E$30 -> 0.55001376 | F35: =F22/F$30 -> 0.5442108 | G35: =G22/G$30 -> 0.5629766
B36: DÍVIDAS | C36: =C23/C$30 -> 0.065625699 | D36: =D23/D$30 -> 0.064200628 | E36: =E23/E$30 -> 0.052510609 | F36: =F23/F$30 -> 0.035525474 | G36: =G23/G$30 -> 0.05404858
B37: SAÚDE | C37: =C24/C$30 -> 0.014512247 | D37: =D24/D$30 -> 0.0070985557 | E37: =E24/E$30 -> 0 | F37: =F24/F$30 -> 0 | G37: =G24/G$30 -> 0.0051814887
B38: TRANSPORTE | C38: =C25/C$30 -> 0.055014608 | D38: =D25/D$30 -> 0.067758941 | E38: =E25/E$30 -> 0.07486907 | F38: =F25/F$30 -> 0.064924662 | G38: =G25/G$30 -> 0.065820608
B39: DESPESAS PESSOAIS | C39: =C26/C$30 -> 0.1627212 | D39: =D26/D$30 -> 0.13351286 | E39: =E26/E$30 -> 0.087651595 | F39: =F26/F$30 -> 0.122863 | G39: =G26/G$30 -> 0.12585867
B40: EDUCAÇÃO | C40: =C27/C$30 -> 0.015831542 | D40: =D27/D$30 -> 0.023231637 | E40: =E27/E$30 -> 0.021912899 | F40: =F27/F$30 -> 0.021681705 | G40: =G27/G$30 -> 0.020725955
B41: LAZER | C41: =C28/C$30 -> 0.021108722 | D41: =D28/D$30 -> 0.010325172 | E41: =E28/E$30 -> 0 | F41: =F28/F$30 -> 0 | G41: =G28/G$30 -> 0.0075367108
B42: OUTROS | C42: =C29/C$30 -> 0.022227485 | D42: =D29/D$30 -> 0.013959632 | E42: =E29/E$30 -> 0 | F42: =F29/F$30 -> 0 | G42: =G29/G$30 -> 0.0086873154
C43: =SUM(C35:C42) -> 0.93403524 | D43: =SUM(D35:D42) -> 0.90320151 | E43: =SUM(E35:E42) -> 0.78695793 | F43: =SUM(F35:F42) -> 0.78920564 | G43: =SUM(G35:G42) -> 0.85083593
B46: ='ORC DOM_2025'!A22 -> BOLETO PESSOAL
B47: ='ORC DOM_2025'!A23 -> META - 1 ano ( pagar divida bitcoin) | C47: ='ORC DOM_2025'!Z23 -> 0
B48: ='ORC DOM_2025'!A24 -> META - 1 ano (quitação do carro) | C48: ='ORC DOM_2025'!Z24 -> 0
B49: ='ORC DOM_2025'!A26 -> META - 8 meses ( Férias Verão) | C49: ='ORC DOM_2025'!Z26 -> 0
B50: ='ORC DOM_2025'!A27 -> METONA ( Casa Própria - 10 anos ) | C50: ='ORC DOM_2025'!Z27 -> 0
B51: ='ORC DOM_2025'!A28 -> METAZONA ( Aposentadoria - 30 anos ) | C51: ='ORC DOM_2025'!Z28 -> 0
B53: ='ORC DOM_2025'!A31 -> HABITAÇÃO
B54: ='ORC DOM_2025'!A32 -> Aluguel | C54: ='ORC DOM_2025'!Z32 -> 8400
B55: ='ORC DOM_2025'!A33 -> Condomínio | C55: ='ORC DOM_2025'!Z33 -> 0
B56: ='ORC DOM_2025'!A34 -> IPTU | C56: ='ORC DOM_2025'!Z34 -> 0
B57: ='ORC DOM_2025'!A35 -> Conta de água | C57: ='ORC DOM_2025'!Z35 -> 555
B58: ='ORC DOM_2025'!A36 -> Conta de energia - 09 | C58: ='ORC DOM_2025'!Z36 -> 416.02
B59: ='ORC DOM_2025'!A37 -> Seguro Residencial | C59: ='ORC DOM_2025'!Z37 -> 0
B60: ='ORC DOM_2025'!A38 -> Conta de gás | C60: ='ORC DOM_2025'!Z38 -> 414.48
B61: ='ORC DOM_2025'!A39 -> Celular+TV+internet | C61: ='ORC DOM_2025'!Z39 -> 432
B62: ='ORC DOM_2025'!A40 -> Celular | C62: ='ORC DOM_2025'!Z40 -> 0
B63: ='ORC DOM_2025'!A41 -> Amazon Prime / Netflix | C63: ='ORC DOM_2025'!Z41 -> 60
B64: ='ORC DOM_2025'!A42 -> Supermercado | C64: ='ORC DOM_2025'!Z42 -> 4800
B65: ='ORC DOM_2025'!A43 -> Feira | C65: ='ORC DOM_2025'!Z43 -> 550
... B67: ='ORC DOM_2025'!A45 -> Faxineira | C67: ='ORC DOM_2025'!Z45 -> 0
B70: ='ORC DOM_2025'!A46 -> DIVÍDAS
B71: ='ORC DOM_2025'!A47 -> Financiamento carro | C71: ='ORC DOM_2025'!Z47 -> 1238.22
B72: ='ORC DOM_2025'!A48 -> Cheque especial | C72: ='ORC DOM_2025'!Z48 -> 0
B73: ='ORC DOM_2025'!A49 -> Empréstimo consignado | C73: ='ORC DOM_2025'!Z49 -> 0
B74: ='ORC DOM_2025'!A50 -> Cartão de crédito em atraso | C74: ='ORC DOM_2025'!Z50 -> 0
B75: ='ORC DOM_2025'!A51 -> Tributos atrasados | C75: ='ORC DOM_2025'!Z51 -> 0
B76: ='ORC DOM_2025'!A52 -> Outros (IPCA) | C76: ='ORC DOM_2025'!Z52 -> 482.91
B79: ='ORC DOM_2025'!A53 -> SAÚDE
B80: ='ORC DOM_2025'!A54 -> Plano de Saúde | C80: ='ORC DOM_2025'!Z54 -> 165
B81: ='ORC DOM_2025'!A55 -> Médicos e terapeutas | C81: ='ORC DOM_2025'!Z55 -> 0
B82: ='ORC DOM_2025'!A56 -> Dentista | C82: ='ORC DOM_2025'!Z56 -> 0
B83: ='ORC DOM_2025'!A57 -> Farmácia | C83: ='ORC DOM_2025'!Z57 -> 0
B84: ='ORC DOM_2025'!A58 -> Outros, se houver | C84: ='ORC DOM_2025'!Z58 -> 0
B87: ='ORC DOM_2025'!A59 -> TRANSPORTE
B88: ='ORC DOM_2025'!A60 -> Licenciamento + multas | C88: ='ORC DOM_2025'!Z60 -> 0
B89: ='ORC DOM_2025'!A61 -> IUC | C89: ='ORC DOM_2025'!Z61 -> 270
B90: ='ORC DOM_2025'!A62 -> Seguro | C90: ='ORC DOM_2025'!Z62 -> 288
B91: ='ORC DOM_2025'!A63 -> Combustível/metro | C91: ='ORC DOM_2025'!Z63 -> 480
B92: ='ORC DOM_2025'!A64 -> Cartao Andante | C92: ='ORC DOM_2025'!Z64 -> 480
B93: ='ORC DOM_2025'!A65 -> Lavagens | C93: ='ORC DOM_2025'!Z65 -> 198
B94: ='ORC DOM_2025'!A66 -> Mecânico / Certificacao anual | C94: ='ORC DOM_2025'!Z66 -> 200
B95: ='ORC DOM_2025'!A67 -> Multas | C95: ='ORC DOM_2025'!Z67 -> 0
B96: ='ORC DOM_2025'!A68 -> Pedágios + tag | C96: ='ORC DOM_2025'!Z68 -> 180
B97: ='ORC DOM_2025'!A69 -> Táxi | C97: ='ORC DOM_2025'!Z69 -> 0
B98: ='ORC DOM_2025'!A70 -> Apps de carro | C98: ='ORC DOM_2025'!Z70 -> 0
B101: ='ORC DOM_2025'!A71 -> DESPESAS PESSOAIS
B102: ='ORC DOM_2025'!A86 -> Mestrado IPCA | C102: ='ORC DOM_2025'!Z86 -> 0
B103: ='ORC DOM_2025'!A72 -> Material escolar | C103: ='ORC DOM_2025'!Z72 -> 0
B104: ='ORC DOM_2025'!A73 -> Higiene Pessoal (unha, depilação etc.) | C104: ='ORC DOM_2025'!Z73 -> 400
B105: ='ORC DOM_2025'!A74 -> Cosméticos | C105: ='ORC DOM_2025'!Z74 -> 500
B106: ='ORC DOM_2025'!A75 -> Cabeleireiro | C106: ='ORC DOM_2025'!Z75 -> 240
B107: ='ORC DOM_2025'!A76 -> Vestuário | C107: ='ORC DOM_2025'!Z76 -> 1200
B108: ='ORC DOM_2025'!A77 -> Academia Sophia | C108: ='ORC DOM_2025'!Z77 -> 385
B109: ='ORC DOM_2025'!A78 -> Seguro de Vida | C109: ='ORC DOM_2025'!Z78 -> 0
B110: ='ORC DOM_2025'!A80 -> Outros - cama (cartão) | C110: ='ORC DOM_2025'!Z80 -> 897.86
B113: ='ORC DOM_2025'!A83 -> EDUCAÇÃO
B114: ='ORC DOM_2025'!A84 -> Cursos Extra Curriculares | C114: ='ORC DOM_2025'!Z84 -> 0
B115: ='ORC DOM_2025'!A85 -> Ingles | C115: ='ORC DOM_2025'!Z85 -> 660
B116: ='ORC DOM_2025'!#REF! -> #ERROR! | C116: ='ORC DOM_2025'!#REF! -> #ERROR!
B118: ='ORC DOM_2025'!A89 -> LAZER
B119: ='ORC DOM_2025'!A90 -> Restaurantes | C119: ='ORC DOM_2025'!Z90 -> 240
B120: ='ORC DOM_2025'!A91 -> Cafés, bares e boates | C120: ='ORC DOM_2025'!Z91 -> 0
B121: ='ORC DOM_2025'!A92 -> Livraria, jornais e revistas | C121: ='ORC DOM_2025'!Z92 -> 0
B122: ='ORC DOM_2025'!A93 -> Spotify, música e outros | C122: ='ORC DOM_2025'!Z93 -> 0
B123: ='ORC DOM_2025'!A94 -> Passeios | C123: ='ORC DOM_2025'!Z94 -> 0
B124: ='ORC DOM_2025'!A95 -> Outros | C124: ='ORC DOM_2025'!Z95 -> 0
B126: ='ORC DOM_2025'!A96 -> OUTROS
...
